{"schema": 4, "pid": 33992, "written_at": "2025-09-10T03-15-51", "stats": {"play": {"Card(A, 5)": {"evals": 257, "sum_wins_evals": 1675, "sum_losses_evals": 3501, "sum_total_candidates_evals": 5651, "certain_evals": 131, "plays": 36, "sum_wins_played": 318, "sum_losses_played": 449, "sum_total_candidates_played": 831, "certain_plays": 15}, "Card(A, 7)": {"evals": 248, "sum_wins_evals": 1909, "sum_losses_evals": 3140, "sum_total_candidates_evals": 5554, "certain_evals": 132, "plays": 32, "sum_wins_played": 290, "sum_losses_played": 292, "sum_total_candidates_played": 634, "certain_plays": 16}, "Card(E, 7)": {"evals": 190, "sum_wins_evals": 2502, "sum_losses_evals": 1786, "sum_total_candidates_evals": 4455, "certain_evals": 66, "plays": 36, "sum_wins_played": 560, "sum_losses_played": 296, "sum_total_candidates_played": 886, "certain_plays": 9}, "Card(D, 3)": {"evals": 107, "sum_wins_evals": 917, "sum_losses_evals": 1692, "sum_total_candidates_evals": 2789, "certain_evals": 42, "plays": 18, "sum_wins_played": 207, "sum_losses_played": 265, "sum_total_candidates_played": 496, "certain_plays": 4}, "Card(D, 5)": {"evals": 221, "sum_wins_evals": 1661, "sum_losses_evals": 2988, "sum_total_candidates_evals": 5236, "certain_evals": 131, "plays": 31, "sum_wins_played": 346, "sum_losses_played": 320, "sum_total_candidates_played": 720, "certain_plays": 13}, "Card(C, 5)": {"evals": 197, "sum_wins_evals": 2850, "sum_losses_evals": 2223, "sum_total_candidates_evals": 5352, "certain_evals": 63, "plays": 36, "sum_wins_played": 711, "sum_losses_played": 326, "sum_total_candidates_played": 1071, "certain_plays": 4}, "Card(B, 1)": {"evals": 116, "sum_wins_evals": 601, "sum_losses_evals": 2270, "sum_total_candidates_evals": 3172, "certain_evals": 64, "plays": 17, "sum_wins_played": 91, "sum_losses_played": 307, "sum_total_candidates_played": 430, "certain_plays": 8}, "Card(E, 9)": {"evals": 81, "sum_wins_evals": 1122, "sum_losses_evals": 711, "sum_total_candidates_evals": 1861, "certain_evals": 31, "plays": 18, "sum_wins_played": 371, "sum_losses_played": 162, "sum_total_candidates_played": 533, "certain_plays": 2}, "Card(D, 7)": {"evals": 196, "sum_wins_evals": 1945, "sum_losses_evals": 2307, "sum_total_candidates_evals": 4730, "certain_evals": 92, "plays": 28, "sum_wins_played": 478, "sum_losses_played": 255, "sum_total_candidates_played": 763, "certain_plays": 5}, "Card(C, 3)": {"evals": 88, "sum_wins_evals": 1095, "sum_losses_evals": 1087, "sum_total_candidates_evals": 2245, "certain_evals": 29, "plays": 16, "sum_wins_played": 225, "sum_losses_played": 149, "sum_total_candidates_played": 374, "certain_plays": 4}, "Card(B, 10)": {"evals": 94, "sum_wins_evals": 845, "sum_losses_evals": 1400, "sum_total_candidates_evals": 2531, "certain_evals": 61, "plays": 10, "sum_wins_played": 237, "sum_losses_played": 51, "sum_total_candidates_played": 294, "certain_plays": 2}, "Card(E, 3)": {"evals": 107, "sum_wins_evals": 1253, "sum_losses_evals": 1727, "sum_total_candidates_evals": 3022, "certain_evals": 21, "plays": 16, "sum_wins_played": 177, "sum_losses_played": 199, "sum_total_candidates_played": 382, "certain_plays": 4}, "Card(D, 11)": {"evals": 72, "sum_wins_evals": 808, "sum_losses_evals": 945, "sum_total_candidates_evals": 1960, "certain_evals": 35, "plays": 15, "sum_wins_played": 246, "sum_losses_played": 78, "sum_total_candidates_played": 332, "certain_plays": 5}, "Card(E, 5)": {"evals": 193, "sum_wins_evals": 2265, "sum_losses_evals": 2264, "sum_total_candidates_evals": 4726, "certain_evals": 64, "plays": 35, "sum_wins_played": 467, "sum_losses_played": 357, "sum_total_candidates_played": 851, "certain_plays": 9}, "Card(B, 3)": {"evals": 111, "sum_wins_evals": 613, "sum_losses_evals": 1731, "sum_total_candidates_evals": 2572, "certain_evals": 70, "plays": 19, "sum_wins_played": 140, "sum_losses_played": 234, "sum_total_candidates_played": 394, "certain_plays": 10}, "Card(B, 11)": {"evals": 86, "sum_wins_evals": 348, "sum_losses_evals": 1326, "sum_total_candidates_evals": 1956, "certain_evals": 71, "plays": 11, "sum_wins_played": 161, "sum_losses_played": 40, "sum_total_candidates_played": 201, "certain_plays": 6}, "Card(E, 11)": {"evals": 60, "sum_wins_evals": 773, "sum_losses_evals": 545, "sum_total_candidates_evals": 1372, "certain_evals": 30, "plays": 17, "sum_wins_played": 306, "sum_losses_played": 82, "sum_total_candidates_played": 388, "certain_plays": 7}, "Card(E, 10)": {"evals": 79, "sum_wins_evals": 950, "sum_losses_evals": 535, "sum_total_candidates_evals": 1514, "certain_evals": 41, "plays": 17, "sum_wins_played": 336, "sum_losses_played": 100, "sum_total_candidates_played": 436, "certain_plays": 5}, "Card(A, 9)": {"evals": 130, "sum_wins_evals": 1106, "sum_losses_evals": 1818, "sum_total_candidates_evals": 3274, "certain_evals": 64, "plays": 16, "sum_wins_played": 194, "sum_losses_played": 146, "sum_total_candidates_played": 366, "certain_plays": 6}, "Card(A, 3)": {"evals": 100, "sum_wins_evals": 632, "sum_losses_evals": 1626, "sum_total_candidates_evals": 2370, "certain_evals": 45, "plays": 16, "sum_wins_played": 131, "sum_losses_played": 222, "sum_total_candidates_played": 359, "certain_plays": 6}, "Card(D, 9)": {"evals": 98, "sum_wins_evals": 698, "sum_losses_evals": 1434, "sum_total_candidates_evals": 2436, "certain_evals": 63, "plays": 13, "sum_wins_played": 181, "sum_losses_played": 99, "sum_total_candidates_played": 293, "certain_plays": 5}, "Card(B, 9)": {"evals": 93, "sum_wins_evals": 646, "sum_losses_evals": 1257, "sum_total_candidates_evals": 2164, "certain_evals": 65, "plays": 13, "sum_wins_played": 143, "sum_losses_played": 78, "sum_total_candidates_played": 235, "certain_plays": 8}, "Card(B, 7)": {"evals": 186, "sum_wins_evals": 1527, "sum_losses_evals": 2435, "sum_total_candidates_evals": 4446, "certain_evals": 117, "plays": 32, "sum_wins_played": 454, "sum_losses_played": 289, "sum_total_candidates_played": 792, "certain_plays": 13}, "Card(C, 10)": {"evals": 63, "sum_wins_evals": 925, "sum_losses_evals": 479, "sum_total_candidates_evals": 1476, "certain_evals": 32, "plays": 18, "sum_wins_played": 413, "sum_losses_played": 66, "sum_total_candidates_played": 481, "certain_plays": 5}, "Card(A, 10)": {"evals": 100, "sum_wins_evals": 796, "sum_losses_evals": 1486, "sum_total_candidates_evals": 2545, "certain_evals": 62, "plays": 14, "sum_wins_played": 200, "sum_losses_played": 94, "sum_total_candidates_played": 301, "certain_plays": 6}, "Card(A, 1)": {"evals": 95, "sum_wins_evals": 410, "sum_losses_evals": 1566, "sum_total_candidates_evals": 2154, "certain_evals": 48, "plays": 13, "sum_wins_played": 68, "sum_losses_played": 204, "sum_total_candidates_played": 285, "certain_plays": 5}, "Card(C, 7)": {"evals": 145, "sum_wins_evals": 1751, "sum_losses_evals": 1296, "sum_total_candidates_evals": 3249, "certain_evals": 72, "plays": 34, "sum_wins_played": 609, "sum_losses_played": 277, "sum_total_candidates_played": 924, "certain_plays": 9}, "Card(C, 9)": {"evals": 63, "sum_wins_evals": 826, "sum_losses_evals": 430, "sum_total_candidates_evals": 1312, "certain_evals": 33, "plays": 17, "sum_wins_played": 320, "sum_losses_played": 55, "sum_total_candidates_played": 375, "certain_plays": 6}, "Card(D, 10)": {"evals": 98, "sum_wins_evals": 729, "sum_losses_evals": 1052, "sum_total_candidates_evals": 2021, "certain_evals": 60, "plays": 13, "sum_wins_played": 162, "sum_losses_played": 69, "sum_total_candidates_played": 237, "certain_plays": 6}, "Card(A, 11)": {"evals": 108, "sum_wins_evals": 834, "sum_losses_evals": 1477, "sum_total_candidates_evals": 2625, "certain_evals": 61, "plays": 14, "sum_wins_played": 204, "sum_losses_played": 103, "sum_total_candidates_played": 320, "certain_plays": 5}, "Card(B, 5)": {"evals": 222, "sum_wins_evals": 1771, "sum_losses_evals": 2949, "sum_total_candidates_evals": 5249, "certain_evals": 134, "plays": 29, "sum_wins_played": 372, "sum_losses_played": 267, "sum_total_candidates_played": 684, "certain_plays": 12}, "Card(D, 1)": {"evals": 112, "sum_wins_evals": 516, "sum_losses_evals": 1773, "sum_total_candidates_evals": 2509, "certain_evals": 63, "plays": 19, "sum_wins_played": 100, "sum_losses_played": 247, "sum_total_candidates_played": 366, "certain_plays": 10}, "Card(C, 11)": {"evals": 44, "sum_wins_evals": 638, "sum_losses_evals": 293, "sum_total_candidates_evals": 977, "certain_evals": 24, "plays": 17, "sum_wins_played": 330, "sum_losses_played": 49, "sum_total_candidates_played": 379, "certain_plays": 8}, "Card(E, 1)": {"evals": 81, "sum_wins_evals": 502, "sum_losses_evals": 1112, "sum_total_candidates_evals": 1614, "certain_evals": 34, "plays": 18, "sum_wins_played": 83, "sum_losses_played": 155, "sum_total_candidates_played": 238, "certain_plays": 11}, "Card(C, 1)": {"evals": 79, "sum_wins_evals": 527, "sum_losses_evals": 1204, "sum_total_candidates_evals": 1829, "certain_evals": 38, "plays": 16, "sum_wins_played": 108, "sum_losses_played": 185, "sum_total_candidates_played": 307, "certain_plays": 8}}, "bet": {"Card(C, 11)": {"evals": 17, "sum_wins_evals": 88, "sum_losses_evals": 16, "sum_total_candidates_evals": 104, "certain_evals": 12, "plays": 17, "sum_wins_played": 88, "sum_losses_played": 16, "sum_total_candidates_played": 104, "certain_plays": 12}, "Card(D, 10)": {"evals": 12, "sum_wins_evals": 55, "sum_losses_evals": 14, "sum_total_candidates_evals": 78, "certain_evals": 6, "plays": 12, "sum_wins_played": 55, "sum_losses_played": 14, "sum_total_candidates_played": 78, "certain_plays": 6}, "Card(A, 11)": {"evals": 13, "sum_wins_evals": 59, "sum_losses_evals": 23, "sum_total_candidates_evals": 84, "certain_evals": 8, "plays": 13, "sum_wins_played": 59, "sum_losses_played": 23, "sum_total_candidates_played": 84, "certain_plays": 8}, "Card(C, 7)": {"evals": 30, "sum_wins_evals": 122, "sum_losses_evals": 40, "sum_total_candidates_evals": 169, "certain_evals": 9, "plays": 30, "sum_wins_played": 122, "sum_losses_played": 40, "sum_total_candidates_played": 169, "certain_plays": 9}, "Card(C, 10)": {"evals": 16, "sum_wins_evals": 77, "sum_losses_evals": 17, "sum_total_candidates_evals": 94, "certain_evals": 9, "plays": 16, "sum_wins_played": 77, "sum_losses_played": 17, "sum_total_candidates_played": 94, "certain_plays": 9}, "Card(C, 9)": {"evals": 17, "sum_wins_evals": 72, "sum_losses_evals": 29, "sum_total_candidates_evals": 101, "certain_evals": 4, "plays": 17, "sum_wins_played": 72, "sum_losses_played": 29, "sum_total_candidates_played": 101, "certain_plays": 4}, "Card(D, 11)": {"evals": 14, "sum_wins_evals": 63, "sum_losses_evals": 29, "sum_total_candidates_evals": 93, "certain_evals": 9, "plays": 14, "sum_wins_played": 63, "sum_losses_played": 29, "sum_total_candidates_played": 93, "certain_plays": 9}, "Card(E, 11)": {"evals": 17, "sum_wins_evals": 85, "sum_losses_evals": 25, "sum_total_candidates_evals": 110, "certain_evals": 9, "plays": 17, "sum_wins_played": 85, "sum_losses_played": 25, "sum_total_candidates_played": 110, "certain_plays": 9}, "Card(E, 10)": {"evals": 15, "sum_wins_evals": 64, "sum_losses_evals": 14, "sum_total_candidates_evals": 78, "certain_evals": 8, "plays": 15, "sum_wins_played": 64, "sum_losses_played": 14, "sum_total_candidates_played": 78, "certain_plays": 8}, "Card(E, 9)": {"evals": 16, "sum_wins_evals": 69, "sum_losses_evals": 30, "sum_total_candidates_evals": 99, "certain_evals": 6, "plays": 16, "sum_wins_played": 69, "sum_losses_played": 30, "sum_total_candidates_played": 99, "certain_plays": 6}, "Card(D, 7)": {"evals": 24, "sum_wins_evals": 68, "sum_losses_evals": 48, "sum_total_candidates_evals": 133, "certain_evals": 7, "plays": 24, "sum_wins_played": 68, "sum_losses_played": 48, "sum_total_candidates_played": 133, "certain_plays": 7}, "Card(C, 5)": {"evals": 34, "sum_wins_evals": 92, "sum_losses_evals": 90, "sum_total_candidates_evals": 189, "certain_evals": 13, "plays": 34, "sum_wins_played": 92, "sum_losses_played": 90, "sum_total_candidates_played": 189, "certain_plays": 13}, "Card(D, 5)": {"evals": 30, "sum_wins_evals": 83, "sum_losses_evals": 94, "sum_total_candidates_evals": 185, "certain_evals": 17, "plays": 30, "sum_wins_played": 83, "sum_losses_played": 94, "sum_total_candidates_played": 185, "certain_plays": 17}, "Card(E, 7)": {"evals": 33, "sum_wins_evals": 134, "sum_losses_evals": 73, "sum_total_candidates_evals": 210, "certain_evals": 12, "plays": 33, "sum_wins_played": 134, "sum_losses_played": 73, "sum_total_candidates_played": 210, "certain_plays": 12}, "Card(D, 9)": {"evals": 11, "sum_wins_evals": 46, "sum_losses_evals": 22, "sum_total_candidates_evals": 71, "certain_evals": 2, "plays": 11, "sum_wins_played": 46, "sum_losses_played": 22, "sum_total_candidates_played": 71, "certain_plays": 2}, "Card(A, 10)": {"evals": 13, "sum_wins_evals": 53, "sum_losses_evals": 24, "sum_total_candidates_evals": 83, "certain_evals": 3, "plays": 13, "sum_wins_played": 53, "sum_losses_played": 24, "sum_total_candidates_played": 83, "certain_plays": 3}, "Card(A, 9)": {"evals": 15, "sum_wins_evals": 62, "sum_losses_evals": 26, "sum_total_candidates_evals": 93, "certain_evals": 6, "plays": 15, "sum_wins_played": 62, "sum_losses_played": 26, "sum_total_candidates_played": 93, "certain_plays": 6}, "Card(E, 5)": {"evals": 33, "sum_wins_evals": 103, "sum_losses_evals": 83, "sum_total_candidates_evals": 194, "certain_evals": 10, "plays": 33, "sum_wins_played": 103, "sum_losses_played": 83, "sum_total_candidates_played": 194, "certain_plays": 10}, "Card(C, 3)": {"evals": 15, "sum_wins_evals": 39, "sum_losses_evals": 43, "sum_total_candidates_evals": 82, "certain_evals": 5, "plays": 15, "sum_wins_played": 39, "sum_losses_played": 43, "sum_total_candidates_played": 82, "certain_plays": 5}, "Card(A, 7)": {"evals": 31, "sum_wins_evals": 91, "sum_losses_evals": 60, "sum_total_candidates_evals": 176, "certain_evals": 14, "plays": 31, "sum_wins_played": 91, "sum_losses_played": 60, "sum_total_candidates_played": 176, "certain_plays": 14}, "Card(D, 1)": {"evals": 19, "sum_wins_evals": 39, "sum_losses_evals": 80, "sum_total_candidates_evals": 121, "certain_evals": 12, "plays": 19, "sum_wins_played": 39, "sum_losses_played": 80, "sum_total_candidates_played": 121, "certain_plays": 12}, "Card(B, 7)": {"evals": 29, "sum_wins_evals": 95, "sum_losses_evals": 66, "sum_total_candidates_evals": 183, "certain_evals": 12, "plays": 29, "sum_wins_played": 95, "sum_losses_played": 66, "sum_total_candidates_played": 183, "certain_plays": 12}, "Card(B, 5)": {"evals": 27, "sum_wins_evals": 68, "sum_losses_evals": 78, "sum_total_candidates_evals": 161, "certain_evals": 14, "plays": 27, "sum_wins_played": 68, "sum_losses_played": 78, "sum_total_candidates_played": 161, "certain_plays": 14}, "Card(A, 1)": {"evals": 13, "sum_wins_evals": 10, "sum_losses_evals": 63, "sum_total_candidates_evals": 86, "certain_evals": 8, "plays": 13, "sum_wins_played": 10, "sum_losses_played": 63, "sum_total_candidates_played": 86, "certain_plays": 8}, "Card(A, 3)": {"evals": 15, "sum_wins_evals": 24, "sum_losses_evals": 53, "sum_total_candidates_evals": 77, "certain_evals": 5, "plays": 15, "sum_wins_played": 24, "sum_losses_played": 53, "sum_total_candidates_played": 77, "certain_plays": 5}, "Card(A, 5)": {"evals": 32, "sum_wins_evals": 70, "sum_losses_evals": 101, "sum_total_candidates_evals": 188, "certain_evals": 14, "plays": 32, "sum_wins_played": 70, "sum_losses_played": 101, "sum_total_candidates_played": 188, "certain_plays": 14}, "Card(D, 3)": {"evals": 18, "sum_wins_evals": 28, "sum_losses_evals": 62, "sum_total_candidates_evals": 99, "certain_evals": 8, "plays": 18, "sum_wins_played": 28, "sum_losses_played": 62, "sum_total_candidates_played": 99, "certain_plays": 8}, "Card(B, 11)": {"evals": 10, "sum_wins_evals": 55, "sum_losses_evals": 16, "sum_total_candidates_evals": 71, "certain_evals": 7, "plays": 10, "sum_wins_played": 55, "sum_losses_played": 16, "sum_total_candidates_played": 71, "certain_plays": 7}, "Card(C, 1)": {"evals": 14, "sum_wins_evals": 16, "sum_losses_evals": 64, "sum_total_candidates_evals": 82, "certain_evals": 10, "plays": 14, "sum_wins_played": 16, "sum_losses_played": 64, "sum_total_candidates_played": 82, "certain_plays": 10}, "Card(B, 1)": {"evals": 16, "sum_wins_evals": 7, "sum_losses_evals": 77, "sum_total_candidates_evals": 86, "certain_evals": 12, "plays": 16, "sum_wins_played": 7, "sum_losses_played": 77, "sum_total_candidates_played": 86, "certain_plays": 12}, "Card(B, 9)": {"evals": 13, "sum_wins_evals": 59, "sum_losses_evals": 23, "sum_total_candidates_evals": 91, "certain_evals": 9, "plays": 13, "sum_wins_played": 59, "sum_losses_played": 23, "sum_total_candidates_played": 91, "certain_plays": 9}, "Card(B, 10)": {"evals": 9, "sum_wins_evals": 47, "sum_losses_evals": 13, "sum_total_candidates_evals": 60, "certain_evals": 5, "plays": 9, "sum_wins_played": 47, "sum_losses_played": 13, "sum_total_candidates_played": 60, "certain_plays": 5}, "Card(E, 1)": {"evals": 15, "sum_wins_evals": 8, "sum_losses_evals": 87, "sum_total_candidates_evals": 95, "certain_evals": 12, "plays": 15, "sum_wins_played": 8, "sum_losses_played": 87, "sum_total_candidates_played": 95, "certain_plays": 12}, "Card(B, 3)": {"evals": 17, "sum_wins_evals": 32, "sum_losses_evals": 70, "sum_total_candidates_evals": 109, "certain_evals": 8, "plays": 17, "sum_wins_played": 32, "sum_losses_played": 70, "sum_total_candidates_played": 109, "certain_plays": 8}, "Card(E, 3)": {"evals": 13, "sum_wins_evals": 35, "sum_losses_evals": 57, "sum_total_candidates_evals": 93, "certain_evals": 5, "plays": 13, "sum_wins_played": 35, "sum_losses_played": 57, "sum_total_candidates_played": 93, "certain_plays": 5}}, "outcome": {"Card(D, 11)": {"wins": 8, "losses": 7, "wins_by_concede": 5, "losses_by_concede": 4}, "Card(E, 9)": {"wins": 11, "losses": 7, "wins_by_concede": 3, "losses_by_concede": 4}, "Card(D, 7)": {"wins": 15, "losses": 13, "wins_by_concede": 9, "losses_by_concede": 7}, "Card(C, 7)": {"wins": 22, "losses": 12, "wins_by_concede": 15, "losses_by_concede": 9}, "Card(C, 5)": {"wins": 20, "losses": 16, "wins_by_concede": 12, "losses_by_concede": 8}, "Card(C, 11)": {"wins": 9, "losses": 8, "wins_by_concede": 3, "losses_by_concede": 7}, "Card(E, 11)": {"wins": 10, "losses": 7, "wins_by_concede": 7, "losses_by_concede": 6}, "Card(C, 10)": {"wins": 10, "losses": 8, "wins_by_concede": 5, "losses_by_concede": 6}, "Card(D, 10)": {"wins": 5, "losses": 8, "wins_by_concede": 3, "losses_by_concede": 4}, "Card(E, 10)": {"wins": 11, "losses": 6, "wins_by_concede": 6, "losses_by_concede": 3}, "Card(A, 11)": {"wins": 10, "losses": 4, "wins_by_concede": 9, "losses_by_concede": 2}, "Card(C, 9)": {"wins": 11, "losses": 6, "wins_by_concede": 10, "losses_by_concede": 3}, "Card(D, 5)": {"wins": 15, "losses": 16, "wins_by_concede": 8, "losses_by_concede": 11}, "Card(E, 5)": {"wins": 16, "losses": 19, "wins_by_concede": 8, "losses_by_concede": 11}, "Card(E, 7)": {"wins": 21, "losses": 15, "wins_by_concede": 9, "losses_by_concede": 10}, "Card(D, 9)": {"wins": 4, "losses": 9, "wins_by_concede": 2, "losses_by_concede": 8}, "Card(A, 7)": {"wins": 14, "losses": 18, "wins_by_concede": 8, "losses_by_concede": 14}, "Card(A, 10)": {"wins": 11, "losses": 3, "wins_by_concede": 6, "losses_by_concede": 2}, "Card(C, 3)": {"wins": 7, "losses": 9, "wins_by_concede": 5, "losses_by_concede": 6}, "Card(A, 9)": {"wins": 7, "losses": 9, "wins_by_concede": 4, "losses_by_concede": 3}, "Card(E, 3)": {"wins": 7, "losses": 9, "wins_by_concede": 4, "losses_by_concede": 7}, "Card(A, 5)": {"wins": 17, "losses": 19, "wins_by_concede": 8, "losses_by_concede": 7}, "Card(A, 1)": {"wins": 2, "losses": 11, "wins_by_concede": 1, "losses_by_concede": 5}, "Card(D, 1)": {"wins": 8, "losses": 11, "wins_by_concede": 6, "losses_by_concede": 5}, "Card(D, 3)": {"wins": 7, "losses": 11, "wins_by_concede": 6, "losses_by_concede": 8}, "Card(B, 3)": {"wins": 8, "losses": 11, "wins_by_concede": 6, "losses_by_concede": 7}, "Card(A, 3)": {"wins": 5, "losses": 11, "wins_by_concede": 4, "losses_by_concede": 6}, "Card(B, 10)": {"wins": 6, "losses": 4, "wins_by_concede": 2, "losses_by_concede": 4}, "Card(B, 7)": {"wins": 13, "losses": 19, "wins_by_concede": 7, "losses_by_concede": 8}, "Card(B, 5)": {"wins": 16, "losses": 13, "wins_by_concede": 8, "losses_by_concede": 6}, "Card(B, 11)": {"wins": 8, "losses": 3, "wins_by_concede": 6, "losses_by_concede": 2}, "Card(B, 9)": {"wins": 9, "losses": 4, "wins_by_concede": 4, "losses_by_concede": 3}, "Card(C, 1)": {"wins": 6, "losses": 10, "wins_by_concede": 6, "losses_by_concede": 4}, "Card(B, 1)": {"wins": 5, "losses": 12, "wins_by_concede": 3, "losses_by_concede": 6}, "Card(E, 1)": {"wins": 6, "losses": 12, "wins_by_concede": 5, "losses_by_concede": 7}}, "coins": {"1": {"uneven_bet_bankCover": 0, "favor_payout_richest": 9, "uneven_bet_add1": 3, "total_domination": 8, "favor_payout_last": 30}, "2": {"uneven_bet_bankCover": 1, "favor_payout_richest": 36, "uneven_bet_add1": 6, "total_domination": 4, "favor_payout_last": 48}, "3": {"uneven_bet_bankCover": 1, "favor_payout_richest": 75, "uneven_bet_add1": 1, "total_domination": 7, "favor_payout_last": 118}, "4": {"uneven_bet_bankCover": 0, "favor_payout_richest": 156, "uneven_bet_add1": 0, "total_domination": 9, "favor_payout_last": 8}}}}