{"schema": 4, "pid": 13892, "written_at": "2025-09-10T03-15-51", "stats": {"play": {"Card(D, 10)": {"evals": 84, "sum_wins_evals": 1108, "sum_losses_evals": 1006, "sum_total_candidates_evals": 2252, "certain_evals": 30, "plays": 16, "sum_wins_played": 269, "sum_losses_played": 88, "sum_total_candidates_played": 357, "certain_plays": 5}, "Card(A, 7)": {"evals": 240, "sum_wins_evals": 1734, "sum_losses_evals": 3203, "sum_total_candidates_evals": 5633, "certain_evals": 133, "plays": 28, "sum_wins_played": 341, "sum_losses_played": 261, "sum_total_candidates_played": 649, "certain_plays": 10}, "Card(A, 11)": {"evals": 75, "sum_wins_evals": 633, "sum_losses_evals": 1034, "sum_total_candidates_evals": 1898, "certain_evals": 50, "plays": 15, "sum_wins_played": 271, "sum_losses_played": 146, "sum_total_candidates_played": 439, "certain_plays": 5}, "Card(B, 7)": {"evals": 198, "sum_wins_evals": 1620, "sum_losses_evals": 2606, "sum_total_candidates_evals": 4783, "certain_evals": 128, "plays": 29, "sum_wins_played": 503, "sum_losses_played": 230, "sum_total_candidates_played": 766, "certain_plays": 8}, "Card(E, 5)": {"evals": 196, "sum_wins_evals": 2129, "sum_losses_evals": 2380, "sum_total_candidates_evals": 4764, "certain_evals": 66, "plays": 33, "sum_wins_played": 377, "sum_losses_played": 317, "sum_total_candidates_played": 733, "certain_plays": 11}, "Card(D, 7)": {"evals": 174, "sum_wins_evals": 1842, "sum_losses_evals": 1679, "sum_total_candidates_evals": 3772, "certain_evals": 79, "plays": 31, "sum_wins_played": 500, "sum_losses_played": 195, "sum_total_candidates_played": 717, "certain_plays": 9}, "Card(B, 3)": {"evals": 99, "sum_wins_evals": 626, "sum_losses_evals": 1615, "sum_total_candidates_evals": 2441, "certain_evals": 55, "plays": 17, "sum_wins_played": 97, "sum_losses_played": 181, "sum_total_candidates_played": 297, "certain_plays": 10}, "Card(C, 11)": {"evals": 74, "sum_wins_evals": 712, "sum_losses_evals": 986, "sum_total_candidates_evals": 1953, "certain_evals": 57, "plays": 14, "sum_wins_played": 336, "sum_losses_played": 44, "sum_total_candidates_played": 380, "certain_plays": 7}, "Card(E, 7)": {"evals": 211, "sum_wins_evals": 2658, "sum_losses_evals": 2313, "sum_total_candidates_evals": 5239, "certain_evals": 67, "plays": 35, "sum_wins_played": 586, "sum_losses_played": 300, "sum_total_candidates_played": 914, "certain_plays": 7}, "Card(C, 10)": {"evals": 87, "sum_wins_evals": 802, "sum_losses_evals": 597, "sum_total_candidates_evals": 1472, "certain_evals": 58, "plays": 16, "sum_wins_played": 255, "sum_losses_played": 55, "sum_total_candidates_played": 312, "certain_plays": 8}, "Card(D, 9)": {"evals": 92, "sum_wins_evals": 1400, "sum_losses_evals": 890, "sum_total_candidates_evals": 2391, "certain_evals": 29, "plays": 18, "sum_wins_played": 309, "sum_losses_played": 129, "sum_total_candidates_played": 449, "certain_plays": 5}, "Card(B, 5)": {"evals": 188, "sum_wins_evals": 1458, "sum_losses_evals": 2700, "sum_total_candidates_evals": 4609, "certain_evals": 114, "plays": 31, "sum_wins_played": 368, "sum_losses_played": 342, "sum_total_candidates_played": 755, "certain_plays": 13}, "Card(C, 1)": {"evals": 110, "sum_wins_evals": 817, "sum_losses_evals": 1867, "sum_total_candidates_evals": 2801, "certain_evals": 44, "plays": 19, "sum_wins_played": 165, "sum_losses_played": 255, "sum_total_candidates_played": 432, "certain_plays": 7}, "Card(C, 5)": {"evals": 190, "sum_wins_evals": 2054, "sum_losses_evals": 2130, "sum_total_candidates_evals": 4488, "certain_evals": 93, "plays": 34, "sum_wins_played": 478, "sum_losses_played": 277, "sum_total_candidates_played": 795, "certain_plays": 13}, "Card(E, 1)": {"evals": 116, "sum_wins_evals": 678, "sum_losses_evals": 1982, "sum_total_candidates_evals": 2708, "certain_evals": 42, "plays": 17, "sum_wins_played": 105, "sum_losses_played": 215, "sum_total_candidates_played": 326, "certain_plays": 7}, "Card(D, 1)": {"evals": 122, "sum_wins_evals": 902, "sum_losses_evals": 2275, "sum_total_candidates_evals": 3292, "certain_evals": 36, "plays": 18, "sum_wins_played": 144, "sum_losses_played": 241, "sum_total_candidates_played": 396, "certain_plays": 6}, "Card(C, 9)": {"evals": 78, "sum_wins_evals": 1047, "sum_losses_evals": 789, "sum_total_candidates_evals": 1961, "certain_evals": 36, "plays": 15, "sum_wins_played": 297, "sum_losses_played": 81, "sum_total_candidates_played": 385, "certain_plays": 4}, "Card(C, 7)": {"evals": 175, "sum_wins_evals": 2186, "sum_losses_evals": 1934, "sum_total_candidates_evals": 4430, "certain_evals": 76, "plays": 30, "sum_wins_played": 534, "sum_losses_played": 198, "sum_total_candidates_played": 749, "certain_plays": 7}, "Card(E, 9)": {"evals": 83, "sum_wins_evals": 1229, "sum_losses_evals": 844, "sum_total_candidates_evals": 2098, "certain_evals": 21, "plays": 16, "sum_wins_played": 253, "sum_losses_played": 126, "sum_total_candidates_played": 384, "certain_plays": 4}, "Card(B, 1)": {"evals": 103, "sum_wins_evals": 436, "sum_losses_evals": 1963, "sum_total_candidates_evals": 2664, "certain_evals": 60, "plays": 17, "sum_wins_played": 82, "sum_losses_played": 232, "sum_total_candidates_played": 340, "certain_plays": 10}, "Card(E, 10)": {"evals": 76, "sum_wins_evals": 783, "sum_losses_evals": 578, "sum_total_candidates_evals": 1434, "certain_evals": 42, "plays": 17, "sum_wins_played": 278, "sum_losses_played": 98, "sum_total_candidates_played": 377, "certain_plays": 7}, "Card(D, 5)": {"evals": 173, "sum_wins_evals": 1511, "sum_losses_evals": 1730, "sum_total_candidates_evals": 3492, "certain_evals": 88, "plays": 32, "sum_wins_played": 402, "sum_losses_played": 264, "sum_total_candidates_played": 696, "certain_plays": 11}, "Card(A, 3)": {"evals": 128, "sum_wins_evals": 652, "sum_losses_evals": 2019, "sum_total_candidates_evals": 2958, "certain_evals": 72, "plays": 16, "sum_wins_played": 126, "sum_losses_played": 263, "sum_total_candidates_played": 422, "certain_plays": 7}, "Card(A, 1)": {"evals": 108, "sum_wins_evals": 654, "sum_losses_evals": 1994, "sum_total_candidates_evals": 2776, "certain_evals": 35, "plays": 18, "sum_wins_played": 109, "sum_losses_played": 262, "sum_total_candidates_played": 385, "certain_plays": 6}, "Card(A, 9)": {"evals": 121, "sum_wins_evals": 888, "sum_losses_evals": 1292, "sum_total_candidates_evals": 2428, "certain_evals": 72, "plays": 15, "sum_wins_played": 152, "sum_losses_played": 112, "sum_total_candidates_played": 283, "certain_plays": 7}, "Card(B, 11)": {"evals": 73, "sum_wins_evals": 496, "sum_losses_evals": 1091, "sum_total_candidates_evals": 1832, "certain_evals": 55, "plays": 16, "sum_wins_played": 276, "sum_losses_played": 148, "sum_total_candidates_played": 444, "certain_plays": 7}, "Card(E, 3)": {"evals": 120, "sum_wins_evals": 1067, "sum_losses_evals": 1721, "sum_total_candidates_evals": 2870, "certain_evals": 42, "plays": 16, "sum_wins_played": 142, "sum_losses_played": 170, "sum_total_candidates_played": 319, "certain_plays": 5}, "Card(C, 3)": {"evals": 105, "sum_wins_evals": 927, "sum_losses_evals": 1405, "sum_total_candidates_evals": 2417, "certain_evals": 47, "plays": 18, "sum_wins_played": 240, "sum_losses_played": 242, "sum_total_candidates_played": 495, "certain_plays": 4}, "Card(D, 11)": {"evals": 68, "sum_wins_evals": 781, "sum_losses_evals": 709, "sum_total_candidates_evals": 1643, "certain_evals": 36, "plays": 16, "sum_wins_played": 291, "sum_losses_played": 80, "sum_total_candidates_played": 377, "certain_plays": 6}, "Card(B, 10)": {"evals": 104, "sum_wins_evals": 801, "sum_losses_evals": 1526, "sum_total_candidates_evals": 2652, "certain_evals": 77, "plays": 13, "sum_wins_played": 267, "sum_losses_played": 42, "sum_total_candidates_played": 310, "certain_plays": 5}, "Card(E, 11)": {"evals": 77, "sum_wins_evals": 1321, "sum_losses_evals": 724, "sum_total_candidates_evals": 2156, "certain_evals": 24, "plays": 19, "sum_wins_played": 354, "sum_losses_played": 102, "sum_total_candidates_played": 462, "certain_plays": 7}, "Card(A, 5)": {"evals": 204, "sum_wins_evals": 1342, "sum_losses_evals": 2938, "sum_total_candidates_evals": 4820, "certain_evals": 113, "plays": 32, "sum_wins_played": 348, "sum_losses_played": 360, "sum_total_candidates_played": 761, "certain_plays": 11}, "Card(D, 3)": {"evals": 103, "sum_wins_evals": 842, "sum_losses_evals": 1421, "sum_total_candidates_evals": 2382, "certain_evals": 46, "plays": 18, "sum_wins_played": 144, "sum_losses_played": 174, "sum_total_candidates_played": 324, "certain_plays": 8}, "Card(B, 9)": {"evals": 62, "sum_wins_evals": 847, "sum_losses_evals": 728, "sum_total_candidates_evals": 1694, "certain_evals": 32, "plays": 12, "sum_wins_played": 264, "sum_losses_played": 76, "sum_total_candidates_played": 340, "certain_plays": 3}, "Card(A, 10)": {"evals": 103, "sum_wins_evals": 934, "sum_losses_evals": 1401, "sum_total_candidates_evals": 2637, "certain_evals": 51, "plays": 13, "sum_wins_played": 240, "sum_losses_played": 103, "sum_total_candidates_played": 358, "certain_plays": 2}}, "bet": {"Card(C, 3)": {"evals": 17, "sum_wins_evals": 50, "sum_losses_evals": 47, "sum_total_candidates_evals": 105, "certain_evals": 8, "plays": 17, "sum_wins_played": 50, "sum_losses_played": 47, "sum_total_candidates_played": 105, "certain_plays": 8}, "Card(E, 11)": {"evals": 18, "sum_wins_evals": 73, "sum_losses_evals": 29, "sum_total_candidates_evals": 103, "certain_evals": 11, "plays": 18, "sum_wins_played": 73, "sum_losses_played": 29, "sum_total_candidates_played": 103, "certain_plays": 11}, "Card(E, 7)": {"evals": 33, "sum_wins_evals": 112, "sum_losses_evals": 73, "sum_total_candidates_evals": 190, "certain_evals": 14, "plays": 33, "sum_wins_played": 112, "sum_losses_played": 73, "sum_total_candidates_played": 190, "certain_plays": 14}, "Card(A, 1)": {"evals": 17, "sum_wins_evals": 10, "sum_losses_evals": 83, "sum_total_candidates_evals": 94, "certain_evals": 9, "plays": 17, "sum_wins_played": 10, "sum_losses_played": 83, "sum_total_candidates_played": 94, "certain_plays": 9}, "Card(C, 5)": {"evals": 33, "sum_wins_evals": 117, "sum_losses_evals": 72, "sum_total_candidates_evals": 201, "certain_evals": 16, "plays": 33, "sum_wins_played": 117, "sum_losses_played": 72, "sum_total_candidates_played": 201, "certain_plays": 16}, "Card(B, 11)": {"evals": 15, "sum_wins_evals": 34, "sum_losses_evals": 43, "sum_total_candidates_evals": 87, "certain_evals": 8, "plays": 15, "sum_wins_played": 34, "sum_losses_played": 43, "sum_total_candidates_played": 87, "certain_plays": 8}, "Card(C, 9)": {"evals": 14, "sum_wins_evals": 62, "sum_losses_evals": 17, "sum_total_candidates_evals": 81, "certain_evals": 5, "plays": 14, "sum_wins_played": 62, "sum_losses_played": 17, "sum_total_candidates_played": 81, "certain_plays": 5}, "Card(C, 7)": {"evals": 29, "sum_wins_evals": 120, "sum_losses_evals": 58, "sum_total_candidates_evals": 188, "certain_evals": 16, "plays": 29, "sum_wins_played": 120, "sum_losses_played": 58, "sum_total_candidates_played": 188, "certain_plays": 16}, "Card(C, 1)": {"evals": 18, "sum_wins_evals": 27, "sum_losses_evals": 83, "sum_total_candidates_evals": 112, "certain_evals": 11, "plays": 18, "sum_wins_played": 27, "sum_losses_played": 83, "sum_total_candidates_played": 112, "certain_plays": 11}, "Card(C, 11)": {"evals": 14, "sum_wins_evals": 72, "sum_losses_evals": 12, "sum_total_candidates_evals": 84, "certain_evals": 10, "plays": 14, "sum_wins_played": 72, "sum_losses_played": 12, "sum_total_candidates_played": 84, "certain_plays": 10}, "Card(C, 10)": {"evals": 16, "sum_wins_evals": 69, "sum_losses_evals": 17, "sum_total_candidates_evals": 101, "certain_evals": 9, "plays": 16, "sum_wins_played": 69, "sum_losses_played": 17, "sum_total_candidates_played": 101, "certain_plays": 9}, "Card(D, 10)": {"evals": 14, "sum_wins_evals": 74, "sum_losses_evals": 14, "sum_total_candidates_evals": 88, "certain_evals": 3, "plays": 14, "sum_wins_played": 74, "sum_losses_played": 14, "sum_total_candidates_played": 88, "certain_plays": 3}, "Card(D, 11)": {"evals": 16, "sum_wins_evals": 66, "sum_losses_evals": 28, "sum_total_candidates_evals": 100, "certain_evals": 11, "plays": 16, "sum_wins_played": 66, "sum_losses_played": 28, "sum_total_candidates_played": 100, "certain_plays": 11}, "Card(B, 10)": {"evals": 12, "sum_wins_evals": 48, "sum_losses_evals": 14, "sum_total_candidates_evals": 68, "certain_evals": 8, "plays": 12, "sum_wins_played": 48, "sum_losses_played": 14, "sum_total_candidates_played": 68, "certain_plays": 8}, "Card(D, 5)": {"evals": 31, "sum_wins_evals": 124, "sum_losses_evals": 65, "sum_total_candidates_evals": 201, "certain_evals": 14, "plays": 31, "sum_wins_played": 124, "sum_losses_played": 65, "sum_total_candidates_played": 201, "certain_plays": 14}, "Card(E, 5)": {"evals": 30, "sum_wins_evals": 102, "sum_losses_evals": 69, "sum_total_candidates_evals": 177, "certain_evals": 10, "plays": 30, "sum_wins_played": 102, "sum_losses_played": 69, "sum_total_candidates_played": 177, "certain_plays": 10}, "Card(E, 10)": {"evals": 17, "sum_wins_evals": 63, "sum_losses_evals": 40, "sum_total_candidates_evals": 110, "certain_evals": 7, "plays": 17, "sum_wins_played": 63, "sum_losses_played": 40, "sum_total_candidates_played": 110, "certain_plays": 7}, "Card(B, 5)": {"evals": 30, "sum_wins_evals": 92, "sum_losses_evals": 77, "sum_total_candidates_evals": 173, "certain_evals": 16, "plays": 30, "sum_wins_played": 92, "sum_losses_played": 77, "sum_total_candidates_played": 173, "certain_plays": 16}, "Card(B, 7)": {"evals": 29, "sum_wins_evals": 109, "sum_losses_evals": 53, "sum_total_candidates_evals": 180, "certain_evals": 14, "plays": 29, "sum_wins_played": 109, "sum_losses_played": 53, "sum_total_candidates_played": 180, "certain_plays": 14}, "Card(D, 7)": {"evals": 31, "sum_wins_evals": 125, "sum_losses_evals": 49, "sum_total_candidates_evals": 193, "certain_evals": 11, "plays": 31, "sum_wins_played": 125, "sum_losses_played": 49, "sum_total_candidates_played": 193, "certain_plays": 11}, "Card(E, 3)": {"evals": 15, "sum_wins_evals": 24, "sum_losses_evals": 53, "sum_total_candidates_evals": 77, "certain_evals": 6, "plays": 15, "sum_wins_played": 24, "sum_losses_played": 53, "sum_total_candidates_played": 77, "certain_plays": 6}, "Card(D, 3)": {"evals": 17, "sum_wins_evals": 16, "sum_losses_evals": 79, "sum_total_candidates_evals": 95, "certain_evals": 8, "plays": 17, "sum_wins_played": 16, "sum_losses_played": 79, "sum_total_candidates_played": 95, "certain_plays": 8}, "Card(B, 1)": {"evals": 16, "sum_wins_evals": 17, "sum_losses_evals": 72, "sum_total_candidates_evals": 99, "certain_evals": 11, "plays": 16, "sum_wins_played": 17, "sum_losses_played": 72, "sum_total_candidates_played": 99, "certain_plays": 11}, "Card(A, 3)": {"evals": 15, "sum_wins_evals": 22, "sum_losses_evals": 60, "sum_total_candidates_evals": 92, "certain_evals": 7, "plays": 15, "sum_wins_played": 22, "sum_losses_played": 60, "sum_total_candidates_played": 92, "certain_plays": 7}, "Card(E, 9)": {"evals": 15, "sum_wins_evals": 72, "sum_losses_evals": 30, "sum_total_candidates_evals": 102, "certain_evals": 4, "plays": 15, "sum_wins_played": 72, "sum_losses_played": 30, "sum_total_candidates_played": 102, "certain_plays": 4}, "Card(D, 9)": {"evals": 18, "sum_wins_evals": 64, "sum_losses_evals": 29, "sum_total_candidates_evals": 93, "certain_evals": 9, "plays": 18, "sum_wins_played": 64, "sum_losses_played": 29, "sum_total_candidates_played": 93, "certain_plays": 9}, "Card(E, 1)": {"evals": 17, "sum_wins_evals": 24, "sum_losses_evals": 64, "sum_total_candidates_evals": 89, "certain_evals": 9, "plays": 17, "sum_wins_played": 24, "sum_losses_played": 64, "sum_total_candidates_played": 89, "certain_plays": 9}, "Card(B, 3)": {"evals": 16, "sum_wins_evals": 30, "sum_losses_evals": 56, "sum_total_candidates_evals": 91, "certain_evals": 10, "plays": 16, "sum_wins_played": 30, "sum_losses_played": 56, "sum_total_candidates_played": 91, "certain_plays": 10}, "Card(A, 7)": {"evals": 27, "sum_wins_evals": 86, "sum_losses_evals": 59, "sum_total_candidates_evals": 158, "certain_evals": 8, "plays": 27, "sum_wins_played": 86, "sum_losses_played": 59, "sum_total_candidates_played": 158, "certain_plays": 8}, "Card(A, 5)": {"evals": 28, "sum_wins_evals": 66, "sum_losses_evals": 91, "sum_total_candidates_evals": 168, "certain_evals": 8, "plays": 28, "sum_wins_played": 66, "sum_losses_played": 91, "sum_total_candidates_played": 168, "certain_plays": 8}, "Card(A, 11)": {"evals": 15, "sum_wins_evals": 50, "sum_losses_evals": 26, "sum_total_candidates_evals": 84, "certain_evals": 6, "plays": 15, "sum_wins_played": 50, "sum_losses_played": 26, "sum_total_candidates_played": 84, "certain_plays": 6}, "Card(A, 10)": {"evals": 12, "sum_wins_evals": 52, "sum_losses_evals": 22, "sum_total_candidates_evals": 84, "certain_evals": 5, "plays": 12, "sum_wins_played": 52, "sum_losses_played": 22, "sum_total_candidates_played": 84, "certain_plays": 5}, "Card(A, 9)": {"evals": 15, "sum_wins_evals": 64, "sum_losses_evals": 27, "sum_total_candidates_evals": 92, "certain_evals": 7, "plays": 15, "sum_wins_played": 64, "sum_losses_played": 27, "sum_total_candidates_played": 92, "certain_plays": 7}, "Card(B, 9)": {"evals": 11, "sum_wins_evals": 47, "sum_losses_evals": 19, "sum_total_candidates_evals": 66, "certain_evals": 3, "plays": 11, "sum_wins_played": 47, "sum_losses_played": 19, "sum_total_candidates_played": 66, "certain_plays": 3}, "Card(D, 1)": {"evals": 16, "sum_wins_evals": 22, "sum_losses_evals": 74, "sum_total_candidates_evals": 99, "certain_evals": 7, "plays": 16, "sum_wins_played": 22, "sum_losses_played": 74, "sum_total_candidates_played": 99, "certain_plays": 7}}, "outcome": {"Card(C, 11)": {"wins": 12, "losses": 2, "wins_by_concede": 8, "losses_by_concede": 1}, "Card(C, 9)": {"wins": 6, "losses": 9, "wins_by_concede": 2, "losses_by_concede": 8}, "Card(C, 10)": {"wins": 12, "losses": 4, "wins_by_concede": 10, "losses_by_concede": 1}, "Card(A, 1)": {"wins": 4, "losses": 14, "wins_by_concede": 2, "losses_by_concede": 8}, "Card(D, 10)": {"wins": 7, "losses": 9, "wins_by_concede": 4, "losses_by_concede": 5}, "Card(C, 3)": {"wins": 8, "losses": 10, "wins_by_concede": 5, "losses_by_concede": 3}, "Card(C, 7)": {"wins": 17, "losses": 13, "wins_by_concede": 10, "losses_by_concede": 8}, "Card(C, 5)": {"wins": 21, "losses": 13, "wins_by_concede": 8, "losses_by_concede": 8}, "Card(E, 11)": {"wins": 12, "losses": 7, "wins_by_concede": 6, "losses_by_concede": 5}, "Card(C, 1)": {"wins": 6, "losses": 13, "wins_by_concede": 3, "losses_by_concede": 6}, "Card(E, 7)": {"wins": 23, "losses": 12, "wins_by_concede": 13, "losses_by_concede": 6}, "Card(B, 11)": {"wins": 6, "losses": 10, "wins_by_concede": 4, "losses_by_concede": 2}, "Card(B, 7)": {"wins": 19, "losses": 10, "wins_by_concede": 10, "losses_by_concede": 4}, "Card(E, 5)": {"wins": 14, "losses": 19, "wins_by_concede": 9, "losses_by_concede": 11}, "Card(D, 11)": {"wins": 9, "losses": 7, "wins_by_concede": 6, "losses_by_concede": 5}, "Card(D, 7)": {"wins": 21, "losses": 10, "wins_by_concede": 11, "losses_by_concede": 7}, "Card(B, 5)": {"wins": 16, "losses": 15, "wins_by_concede": 5, "losses_by_concede": 8}, "Card(D, 5)": {"wins": 19, "losses": 13, "wins_by_concede": 10, "losses_by_concede": 7}, "Card(B, 10)": {"wins": 8, "losses": 5, "wins_by_concede": 6, "losses_by_concede": 4}, "Card(E, 10)": {"wins": 7, "losses": 10, "wins_by_concede": 4, "losses_by_concede": 5}, "Card(E, 9)": {"wins": 8, "losses": 8, "wins_by_concede": 2, "losses_by_concede": 4}, "Card(B, 3)": {"wins": 5, "losses": 12, "wins_by_concede": 3, "losses_by_concede": 4}, "Card(A, 7)": {"wins": 18, "losses": 10, "wins_by_concede": 9, "losses_by_concede": 5}, "Card(B, 1)": {"wins": 2, "losses": 15, "wins_by_concede": 2, "losses_by_concede": 7}, "Card(D, 9)": {"wins": 8, "losses": 10, "wins_by_concede": 4, "losses_by_concede": 6}, "Card(E, 3)": {"wins": 6, "losses": 10, "wins_by_concede": 3, "losses_by_concede": 5}, "Card(E, 1)": {"wins": 6, "losses": 11, "wins_by_concede": 4, "losses_by_concede": 7}, "Card(D, 3)": {"wins": 5, "losses": 13, "wins_by_concede": 4, "losses_by_concede": 8}, "Card(A, 3)": {"wins": 6, "losses": 10, "wins_by_concede": 5, "losses_by_concede": 8}, "Card(A, 11)": {"wins": 9, "losses": 6, "wins_by_concede": 3, "losses_by_concede": 6}, "Card(D, 1)": {"wins": 5, "losses": 13, "wins_by_concede": 1, "losses_by_concede": 7}, "Card(A, 5)": {"wins": 13, "losses": 19, "wins_by_concede": 7, "losses_by_concede": 8}, "Card(A, 10)": {"wins": 6, "losses": 7, "wins_by_concede": 4, "losses_by_concede": 4}, "Card(A, 9)": {"wins": 8, "losses": 7, "wins_by_concede": 5, "losses_by_concede": 5}, "Card(B, 9)": {"wins": 8, "losses": 4, "wins_by_concede": 6, "losses_by_concede": 2}}, "coins": {"1": {"favor_payout_last": 54, "uneven_bet_add1": 4, "favor_payout_richest": 8, "total_domination": 3, "uneven_bet_bankCover": 1}, "2": {"favor_payout_last": 29, "uneven_bet_add1": 9, "favor_payout_richest": 48, "total_domination": 4, "uneven_bet_bankCover": 2}, "3": {"favor_payout_last": 39, "uneven_bet_add1": 0, "favor_payout_richest": 50, "total_domination": 10, "uneven_bet_bankCover": 0}, "4": {"favor_payout_last": 21, "uneven_bet_add1": 0, "favor_payout_richest": 80, "total_domination": 12, "uneven_bet_bankCover": 0}}}}