{"schema": 4, "pid": 32256, "written_at": "2025-09-10T03-11-01", "stats": {"play": {"Card(C, 5)": {"evals": 203, "sum_wins_evals": 2358, "sum_losses_evals": 2186, "sum_total_candidates_evals": 4786, "certain_evals": 71, "plays": 37, "sum_wins_played": 516, "sum_losses_played": 368, "sum_total_candidates_played": 923, "certain_plays": 10}, "Card(B, 3)": {"evals": 113, "sum_wins_evals": 433, "sum_losses_evals": 2019, "sum_total_candidates_evals": 2870, "certain_evals": 71, "plays": 13, "sum_wins_played": 62, "sum_losses_played": 163, "sum_total_candidates_played": 251, "certain_plays": 7}, "Card(A, 11)": {"evals": 75, "sum_wins_evals": 1023, "sum_losses_evals": 636, "sum_total_candidates_evals": 1785, "certain_evals": 36, "plays": 17, "sum_wins_played": 333, "sum_losses_played": 81, "sum_total_candidates_played": 421, "certain_plays": 6}, "Card(A, 3)": {"evals": 126, "sum_wins_evals": 1268, "sum_losses_evals": 1938, "sum_total_candidates_evals": 3294, "certain_evals": 37, "plays": 20, "sum_wins_played": 201, "sum_losses_played": 243, "sum_total_candidates_played": 451, "certain_plays": 6}, "Card(C, 3)": {"evals": 83, "sum_wins_evals": 1071, "sum_losses_evals": 1156, "sum_total_candidates_evals": 2281, "certain_evals": 15, "plays": 16, "sum_wins_played": 195, "sum_losses_played": 155, "sum_total_candidates_played": 356, "certain_plays": 5}, "Card(A, 9)": {"evals": 82, "sum_wins_evals": 714, "sum_losses_evals": 995, "sum_total_candidates_evals": 1905, "certain_evals": 50, "plays": 14, "sum_wins_played": 219, "sum_losses_played": 78, "sum_total_candidates_played": 304, "certain_plays": 6}, "Card(B, 10)": {"evals": 111, "sum_wins_evals": 552, "sum_losses_evals": 1469, "sum_total_candidates_evals": 2383, "certain_evals": 76, "plays": 15, "sum_wins_played": 157, "sum_losses_played": 159, "sum_total_candidates_played": 350, "certain_plays": 8}, "Card(D, 7)": {"evals": 179, "sum_wins_evals": 1946, "sum_losses_evals": 2144, "sum_total_candidates_evals": 4529, "certain_evals": 99, "plays": 29, "sum_wins_played": 563, "sum_losses_played": 177, "sum_total_candidates_played": 763, "certain_plays": 8}, "Card(D, 5)": {"evals": 161, "sum_wins_evals": 1721, "sum_losses_evals": 1933, "sum_total_candidates_evals": 3990, "certain_evals": 84, "plays": 32, "sum_wins_played": 519, "sum_losses_played": 266, "sum_total_candidates_played": 823, "certain_plays": 10}, "Card(E, 7)": {"evals": 181, "sum_wins_evals": 1893, "sum_losses_evals": 2271, "sum_total_candidates_evals": 4638, "certain_evals": 75, "plays": 29, "sum_wins_played": 418, "sum_losses_played": 231, "sum_total_candidates_played": 689, "certain_plays": 8}, "Card(D, 1)": {"evals": 90, "sum_wins_evals": 790, "sum_losses_evals": 1589, "sum_total_candidates_evals": 2527, "certain_evals": 36, "plays": 17, "sum_wins_played": 171, "sum_losses_played": 261, "sum_total_candidates_played": 446, "certain_plays": 5}, "Card(C, 11)": {"evals": 64, "sum_wins_evals": 1126, "sum_losses_evals": 501, "sum_total_candidates_evals": 1708, "certain_evals": 29, "plays": 18, "sum_wins_played": 365, "sum_losses_played": 75, "sum_total_candidates_played": 446, "certain_plays": 9}, "Card(E, 11)": {"evals": 86, "sum_wins_evals": 972, "sum_losses_evals": 1024, "sum_total_candidates_evals": 2201, "certain_evals": 38, "plays": 16, "sum_wins_played": 345, "sum_losses_played": 112, "sum_total_candidates_played": 471, "certain_plays": 5}, "Card(C, 7)": {"evals": 183, "sum_wins_evals": 2579, "sum_losses_evals": 1846, "sum_total_candidates_evals": 4656, "certain_evals": 59, "plays": 37, "sum_wins_played": 720, "sum_losses_played": 329, "sum_total_candidates_played": 1087, "certain_plays": 5}, "Card(B, 7)": {"evals": 269, "sum_wins_evals": 1443, "sum_losses_evals": 4137, "sum_total_candidates_evals": 6557, "certain_evals": 168, "plays": 30, "sum_wins_played": 256, "sum_losses_played": 419, "sum_total_candidates_played": 773, "certain_plays": 12}, "Card(E, 10)": {"evals": 69, "sum_wins_evals": 590, "sum_losses_evals": 760, "sum_total_candidates_evals": 1495, "certain_evals": 38, "plays": 13, "sum_wins_played": 154, "sum_losses_played": 72, "sum_total_candidates_played": 237, "certain_plays": 6}, "Card(E, 5)": {"evals": 207, "sum_wins_evals": 1998, "sum_losses_evals": 2767, "sum_total_candidates_evals": 5289, "certain_evals": 85, "plays": 33, "sum_wins_played": 500, "sum_losses_played": 416, "sum_total_candidates_played": 984, "certain_plays": 5}, "Card(B, 9)": {"evals": 122, "sum_wins_evals": 505, "sum_losses_evals": 1814, "sum_total_candidates_evals": 2793, "certain_evals": 81, "plays": 11, "sum_wins_played": 92, "sum_losses_played": 79, "sum_total_candidates_played": 187, "certain_plays": 5}, "Card(B, 1)": {"evals": 121, "sum_wins_evals": 534, "sum_losses_evals": 2244, "sum_total_candidates_evals": 3178, "certain_evals": 71, "plays": 15, "sum_wins_played": 90, "sum_losses_played": 278, "sum_total_candidates_played": 416, "certain_plays": 7}, "Card(B, 5)": {"evals": 241, "sum_wins_evals": 1120, "sum_losses_evals": 3798, "sum_total_candidates_evals": 5774, "certain_evals": 150, "plays": 29, "sum_wins_played": 214, "sum_losses_played": 373, "sum_total_candidates_played": 668, "certain_plays": 14}, "Card(C, 1)": {"evals": 76, "sum_wins_evals": 735, "sum_losses_evals": 1189, "sum_total_candidates_evals": 1924, "certain_evals": 19, "plays": 17, "sum_wins_played": 133, "sum_losses_played": 217, "sum_total_candidates_played": 350, "certain_plays": 6}, "Card(E, 3)": {"evals": 110, "sum_wins_evals": 924, "sum_losses_evals": 1609, "sum_total_candidates_evals": 2738, "certain_evals": 49, "plays": 20, "sum_wins_played": 186, "sum_losses_played": 230, "sum_total_candidates_played": 436, "certain_plays": 8}, "Card(D, 11)": {"evals": 87, "sum_wins_evals": 965, "sum_losses_evals": 1162, "sum_total_candidates_evals": 2402, "certain_evals": 61, "plays": 16, "sum_wins_played": 347, "sum_losses_played": 61, "sum_total_candidates_played": 409, "certain_plays": 8}, "Card(A, 1)": {"evals": 91, "sum_wins_evals": 512, "sum_losses_evals": 1563, "sum_total_candidates_evals": 2249, "certain_evals": 51, "plays": 18, "sum_wins_played": 78, "sum_losses_played": 197, "sum_total_candidates_played": 295, "certain_plays": 12}, "Card(D, 10)": {"evals": 75, "sum_wins_evals": 934, "sum_losses_evals": 756, "sum_total_candidates_evals": 1823, "certain_evals": 41, "plays": 16, "sum_wins_played": 329, "sum_losses_played": 56, "sum_total_candidates_played": 385, "certain_plays": 5}, "Card(A, 5)": {"evals": 203, "sum_wins_evals": 1951, "sum_losses_evals": 2724, "sum_total_candidates_evals": 5053, "certain_evals": 82, "plays": 32, "sum_wins_played": 351, "sum_losses_played": 295, "sum_total_candidates_played": 687, "certain_plays": 12}, "Card(A, 10)": {"evals": 92, "sum_wins_evals": 921, "sum_losses_evals": 1094, "sum_total_candidates_evals": 2196, "certain_evals": 48, "plays": 16, "sum_wins_played": 286, "sum_losses_played": 93, "sum_total_candidates_played": 384, "certain_plays": 5}, "Card(C, 9)": {"evals": 77, "sum_wins_evals": 1176, "sum_losses_evals": 761, "sum_total_candidates_evals": 2024, "certain_evals": 22, "plays": 17, "sum_wins_played": 343, "sum_losses_played": 119, "sum_total_candidates_played": 469, "certain_plays": 4}, "Card(B, 11)": {"evals": 119, "sum_wins_evals": 634, "sum_losses_evals": 1868, "sum_total_candidates_evals": 2973, "certain_evals": 81, "plays": 12, "sum_wins_played": 151, "sum_losses_played": 93, "sum_total_candidates_played": 261, "certain_plays": 6}, "Card(E, 9)": {"evals": 92, "sum_wins_evals": 948, "sum_losses_evals": 1199, "sum_total_candidates_evals": 2420, "certain_evals": 37, "plays": 17, "sum_wins_played": 253, "sum_losses_played": 165, "sum_total_candidates_played": 454, "certain_plays": 5}, "Card(A, 7)": {"evals": 218, "sum_wins_evals": 2355, "sum_losses_evals": 2490, "sum_total_candidates_evals": 5212, "certain_evals": 93, "plays": 35, "sum_wins_played": 500, "sum_losses_played": 293, "sum_total_candidates_played": 830, "certain_plays": 11}, "Card(D, 9)": {"evals": 81, "sum_wins_evals": 775, "sum_losses_evals": 809, "sum_total_candidates_evals": 1720, "certain_evals": 52, "plays": 15, "sum_wins_played": 283, "sum_losses_played": 79, "sum_total_candidates_played": 370, "certain_plays": 5}, "Card(D, 3)": {"evals": 80, "sum_wins_evals": 690, "sum_losses_evals": 1144, "sum_total_candidates_evals": 1973, "certain_evals": 43, "plays": 16, "sum_wins_played": 210, "sum_losses_played": 187, "sum_total_candidates_played": 411, "certain_plays": 5}, "Card(C, 10)": {"evals": 62, "sum_wins_evals": 818, "sum_losses_evals": 549, "sum_total_candidates_evals": 1443, "certain_evals": 29, "plays": 15, "sum_wins_played": 311, "sum_losses_played": 90, "sum_total_candidates_played": 409, "certain_plays": 5}, "Card(E, 1)": {"evals": 91, "sum_wins_evals": 598, "sum_losses_evals": 1442, "sum_total_candidates_evals": 2164, "certain_evals": 38, "plays": 17, "sum_wins_played": 87, "sum_losses_played": 180, "sum_total_candidates_played": 280, "certain_plays": 9}}, "bet": {"Card(D, 5)": {"evals": 27, "sum_wins_evals": 82, "sum_losses_evals": 63, "sum_total_candidates_evals": 150, "certain_evals": 12, "plays": 27, "sum_wins_played": 82, "sum_losses_played": 63, "sum_total_candidates_played": 150, "certain_plays": 12}, "Card(C, 9)": {"evals": 16, "sum_wins_evals": 59, "sum_losses_evals": 25, "sum_total_candidates_evals": 84, "certain_evals": 9, "plays": 16, "sum_wins_played": 59, "sum_losses_played": 25, "sum_total_candidates_played": 84, "certain_plays": 9}, "Card(A, 5)": {"evals": 30, "sum_wins_evals": 95, "sum_losses_evals": 79, "sum_total_candidates_evals": 186, "certain_evals": 12, "plays": 30, "sum_wins_played": 95, "sum_losses_played": 79, "sum_total_candidates_played": 186, "certain_plays": 12}, "Card(D, 11)": {"evals": 15, "sum_wins_evals": 69, "sum_losses_evals": 15, "sum_total_candidates_evals": 92, "certain_evals": 12, "plays": 15, "sum_wins_played": 69, "sum_losses_played": 15, "sum_total_candidates_played": 92, "certain_plays": 12}, "Card(D, 10)": {"evals": 15, "sum_wins_evals": 69, "sum_losses_evals": 32, "sum_total_candidates_evals": 101, "certain_evals": 5, "plays": 15, "sum_wins_played": 69, "sum_losses_played": 32, "sum_total_candidates_played": 101, "certain_plays": 5}, "Card(C, 5)": {"evals": 32, "sum_wins_evals": 103, "sum_losses_evals": 68, "sum_total_candidates_evals": 175, "certain_evals": 15, "plays": 32, "sum_wins_played": 103, "sum_losses_played": 68, "sum_total_candidates_played": 175, "certain_plays": 15}, "Card(C, 7)": {"evals": 34, "sum_wins_evals": 115, "sum_losses_evals": 74, "sum_total_candidates_evals": 195, "certain_evals": 9, "plays": 34, "sum_wins_played": 115, "sum_losses_played": 74, "sum_total_candidates_played": 195, "certain_plays": 9}, "Card(C, 11)": {"evals": 16, "sum_wins_evals": 72, "sum_losses_evals": 29, "sum_total_candidates_evals": 101, "certain_evals": 12, "plays": 16, "sum_wins_played": 72, "sum_losses_played": 29, "sum_total_candidates_played": 101, "certain_plays": 12}, "Card(A, 9)": {"evals": 14, "sum_wins_evals": 64, "sum_losses_evals": 26, "sum_total_candidates_evals": 92, "certain_evals": 4, "plays": 14, "sum_wins_played": 64, "sum_losses_played": 26, "sum_total_candidates_played": 92, "certain_plays": 4}, "Card(A, 11)": {"evals": 17, "sum_wins_evals": 81, "sum_losses_evals": 19, "sum_total_candidates_evals": 108, "certain_evals": 11, "plays": 17, "sum_wins_played": 81, "sum_losses_played": 19, "sum_total_candidates_played": 108, "certain_plays": 11}, "Card(A, 10)": {"evals": 15, "sum_wins_evals": 70, "sum_losses_evals": 19, "sum_total_candidates_evals": 89, "certain_evals": 6, "plays": 15, "sum_wins_played": 70, "sum_losses_played": 19, "sum_total_candidates_played": 89, "certain_plays": 6}, "Card(D, 9)": {"evals": 14, "sum_wins_evals": 61, "sum_losses_evals": 15, "sum_total_candidates_evals": 83, "certain_evals": 7, "plays": 14, "sum_wins_played": 61, "sum_losses_played": 15, "sum_total_candidates_played": 83, "certain_plays": 7}, "Card(E, 9)": {"evals": 15, "sum_wins_evals": 67, "sum_losses_evals": 27, "sum_total_candidates_evals": 99, "certain_evals": 6, "plays": 15, "sum_wins_played": 67, "sum_losses_played": 27, "sum_total_candidates_played": 99, "certain_plays": 6}, "Card(A, 1)": {"evals": 14, "sum_wins_evals": 22, "sum_losses_evals": 69, "sum_total_candidates_evals": 91, "certain_evals": 10, "plays": 14, "sum_wins_played": 22, "sum_losses_played": 69, "sum_total_candidates_played": 91, "certain_plays": 10}, "Card(C, 1)": {"evals": 14, "sum_wins_evals": 30, "sum_losses_evals": 63, "sum_total_candidates_evals": 93, "certain_evals": 6, "plays": 14, "sum_wins_played": 30, "sum_losses_played": 63, "sum_total_candidates_played": 93, "certain_plays": 6}, "Card(B, 1)": {"evals": 10, "sum_wins_evals": 2, "sum_losses_evals": 49, "sum_total_candidates_evals": 61, "certain_evals": 8, "plays": 10, "sum_wins_played": 2, "sum_losses_played": 49, "sum_total_candidates_played": 61, "certain_plays": 8}, "Card(D, 7)": {"evals": 27, "sum_wins_evals": 129, "sum_losses_evals": 31, "sum_total_candidates_evals": 164, "certain_evals": 15, "plays": 27, "sum_wins_played": 129, "sum_losses_played": 31, "sum_total_candidates_played": 164, "certain_plays": 15}, "Card(C, 3)": {"evals": 13, "sum_wins_evals": 26, "sum_losses_evals": 36, "sum_total_candidates_evals": 68, "certain_evals": 6, "plays": 13, "sum_wins_played": 26, "sum_losses_played": 36, "sum_total_candidates_played": 68, "certain_plays": 6}, "Card(A, 7)": {"evals": 30, "sum_wins_evals": 107, "sum_losses_evals": 44, "sum_total_candidates_evals": 168, "certain_evals": 12, "plays": 30, "sum_wins_played": 107, "sum_losses_played": 44, "sum_total_candidates_played": 168, "certain_plays": 12}, "Card(B, 5)": {"evals": 24, "sum_wins_evals": 39, "sum_losses_evals": 90, "sum_total_candidates_evals": 151, "certain_evals": 11, "plays": 24, "sum_wins_played": 39, "sum_losses_played": 90, "sum_total_candidates_played": 151, "certain_plays": 11}, "Card(E, 3)": {"evals": 17, "sum_wins_evals": 21, "sum_losses_evals": 84, "sum_total_candidates_evals": 107, "certain_evals": 7, "plays": 17, "sum_wins_played": 21, "sum_losses_played": 84, "sum_total_candidates_played": 107, "certain_plays": 7}, "Card(E, 5)": {"evals": 26, "sum_wins_evals": 69, "sum_losses_evals": 65, "sum_total_candidates_evals": 149, "certain_evals": 8, "plays": 26, "sum_wins_played": 69, "sum_losses_played": 65, "sum_total_candidates_played": 149, "certain_plays": 8}, "Card(E, 1)": {"evals": 13, "sum_wins_evals": 19, "sum_losses_evals": 70, "sum_total_candidates_evals": 89, "certain_evals": 9, "plays": 13, "sum_wins_played": 19, "sum_losses_played": 70, "sum_total_candidates_played": 89, "certain_plays": 9}, "Card(C, 10)": {"evals": 13, "sum_wins_evals": 52, "sum_losses_evals": 35, "sum_total_candidates_evals": 87, "certain_evals": 5, "plays": 13, "sum_wins_played": 52, "sum_losses_played": 35, "sum_total_candidates_played": 87, "certain_plays": 5}, "Card(E, 10)": {"evals": 10, "sum_wins_evals": 38, "sum_losses_evals": 15, "sum_total_candidates_evals": 59, "certain_evals": 4, "plays": 10, "sum_wins_played": 38, "sum_losses_played": 15, "sum_total_candidates_played": 59, "certain_plays": 4}, "Card(E, 7)": {"evals": 21, "sum_wins_evals": 67, "sum_losses_evals": 47, "sum_total_candidates_evals": 121, "certain_evals": 3, "plays": 21, "sum_wins_played": 67, "sum_losses_played": 47, "sum_total_candidates_played": 121, "certain_plays": 3}, "Card(E, 11)": {"evals": 16, "sum_wins_evals": 65, "sum_losses_evals": 21, "sum_total_candidates_evals": 90, "certain_evals": 7, "plays": 16, "sum_wins_played": 65, "sum_losses_played": 21, "sum_total_candidates_played": 90, "certain_plays": 7}, "Card(D, 3)": {"evals": 16, "sum_wins_evals": 40, "sum_losses_evals": 50, "sum_total_candidates_evals": 97, "certain_evals": 5, "plays": 16, "sum_wins_played": 40, "sum_losses_played": 50, "sum_total_candidates_played": 97, "certain_plays": 5}, "Card(B, 10)": {"evals": 11, "sum_wins_evals": 29, "sum_losses_evals": 29, "sum_total_candidates_evals": 78, "certain_evals": 7, "plays": 11, "sum_wins_played": 29, "sum_losses_played": 29, "sum_total_candidates_played": 78, "certain_plays": 7}, "Card(B, 3)": {"evals": 11, "sum_wins_evals": 8, "sum_losses_evals": 49, "sum_total_candidates_evals": 64, "certain_evals": 5, "plays": 11, "sum_wins_played": 8, "sum_losses_played": 49, "sum_total_candidates_played": 64, "certain_plays": 5}, "Card(B, 11)": {"evals": 10, "sum_wins_evals": 38, "sum_losses_evals": 27, "sum_total_candidates_evals": 66, "certain_evals": 4, "plays": 10, "sum_wins_played": 38, "sum_losses_played": 27, "sum_total_candidates_played": 66, "certain_plays": 4}, "Card(A, 3)": {"evals": 16, "sum_wins_evals": 29, "sum_losses_evals": 69, "sum_total_candidates_evals": 98, "certain_evals": 8, "plays": 16, "sum_wins_played": 29, "sum_losses_played": 69, "sum_total_candidates_played": 98, "certain_plays": 8}, "Card(B, 9)": {"evals": 10, "sum_wins_evals": 45, "sum_losses_evals": 28, "sum_total_candidates_evals": 75, "certain_evals": 4, "plays": 10, "sum_wins_played": 45, "sum_losses_played": 28, "sum_total_candidates_played": 75, "certain_plays": 4}, "Card(D, 1)": {"evals": 13, "sum_wins_evals": 22, "sum_losses_evals": 48, "sum_total_candidates_evals": 71, "certain_evals": 4, "plays": 13, "sum_wins_played": 22, "sum_losses_played": 48, "sum_total_candidates_played": 71, "certain_plays": 4}, "Card(B, 7)": {"evals": 26, "sum_wins_evals": 41, "sum_losses_evals": 82, "sum_total_candidates_evals": 140, "certain_evals": 14, "plays": 26, "sum_wins_played": 41, "sum_losses_played": 82, "sum_total_candidates_played": 140, "certain_plays": 14}}, "outcome": {"Card(C, 5)": {"wins": 20, "losses": 17, "wins_by_concede": 8, "losses_by_concede": 12}, "Card(D, 5)": {"wins": 15, "losses": 17, "wins_by_concede": 9, "losses_by_concede": 12}, "Card(A, 9)": {"wins": 9, "losses": 5, "wins_by_concede": 5, "losses_by_concede": 3}, "Card(D, 11)": {"wins": 12, "losses": 4, "wins_by_concede": 9, "losses_by_concede": 3}, "Card(A, 11)": {"wins": 10, "losses": 7, "wins_by_concede": 6, "losses_by_concede": 5}, "Card(C, 7)": {"wins": 20, "losses": 17, "wins_by_concede": 9, "losses_by_concede": 12}, "Card(D, 10)": {"wins": 12, "losses": 4, "wins_by_concede": 7, "losses_by_concede": 2}, "Card(C, 11)": {"wins": 12, "losses": 6, "wins_by_concede": 10, "losses_by_concede": 4}, "Card(C, 9)": {"wins": 9, "losses": 8, "wins_by_concede": 2, "losses_by_concede": 5}, "Card(A, 5)": {"wins": 14, "losses": 18, "wins_by_concede": 9, "losses_by_concede": 9}, "Card(D, 7)": {"wins": 14, "losses": 15, "wins_by_concede": 3, "losses_by_concede": 8}, "Card(D, 1)": {"wins": 2, "losses": 15, "wins_by_concede": 1, "losses_by_concede": 5}, "Card(A, 1)": {"wins": 5, "losses": 13, "wins_by_concede": 3, "losses_by_concede": 5}, "Card(A, 10)": {"wins": 12, "losses": 4, "wins_by_concede": 9, "losses_by_concede": 3}, "Card(C, 3)": {"wins": 6, "losses": 10, "wins_by_concede": 4, "losses_by_concede": 3}, "Card(C, 1)": {"wins": 8, "losses": 9, "wins_by_concede": 6, "losses_by_concede": 4}, "Card(E, 5)": {"wins": 12, "losses": 21, "wins_by_concede": 6, "losses_by_concede": 11}, "Card(E, 10)": {"wins": 5, "losses": 8, "wins_by_concede": 2, "losses_by_concede": 6}, "Card(D, 9)": {"wins": 10, "losses": 5, "wins_by_concede": 8, "losses_by_concede": 4}, "Card(E, 9)": {"wins": 12, "losses": 5, "wins_by_concede": 7, "losses_by_concede": 1}, "Card(B, 1)": {"wins": 4, "losses": 11, "wins_by_concede": 3, "losses_by_concede": 4}, "Card(E, 7)": {"wins": 18, "losses": 11, "wins_by_concede": 8, "losses_by_concede": 5}, "Card(A, 3)": {"wins": 9, "losses": 11, "wins_by_concede": 5, "losses_by_concede": 5}, "Card(E, 3)": {"wins": 8, "losses": 12, "wins_by_concede": 3, "losses_by_concede": 3}, "Card(B, 10)": {"wins": 9, "losses": 6, "wins_by_concede": 6, "losses_by_concede": 4}, "Card(B, 7)": {"wins": 12, "losses": 18, "wins_by_concede": 8, "losses_by_concede": 9}, "Card(A, 7)": {"wins": 19, "losses": 16, "wins_by_concede": 7, "losses_by_concede": 11}, "Card(B, 5)": {"wins": 13, "losses": 16, "wins_by_concede": 7, "losses_by_concede": 9}, "Card(C, 10)": {"wins": 9, "losses": 6, "wins_by_concede": 6, "losses_by_concede": 5}, "Card(E, 1)": {"wins": 5, "losses": 12, "wins_by_concede": 1, "losses_by_concede": 6}, "Card(E, 11)": {"wins": 11, "losses": 5, "wins_by_concede": 5, "losses_by_concede": 5}, "Card(D, 3)": {"wins": 9, "losses": 7, "wins_by_concede": 7, "losses_by_concede": 5}, "Card(B, 3)": {"wins": 2, "losses": 11, "wins_by_concede": 2, "losses_by_concede": 5}, "Card(B, 11)": {"wins": 5, "losses": 7, "wins_by_concede": 3, "losses_by_concede": 4}, "Card(B, 9)": {"wins": 8, "losses": 3, "wins_by_concede": 5, "losses_by_concede": 2}}, "coins": {"1": {"favor_payout_richest": 8, "uneven_bet_bankCover": 1, "favor_payout_last": 72, "total_domination": 7, "uneven_bet_add1": 15}, "2": {"favor_payout_richest": 66, "uneven_bet_bankCover": 2, "favor_payout_last": 59, "total_domination": 3, "uneven_bet_add1": 12}, "3": {"favor_payout_richest": 38, "uneven_bet_bankCover": 0, "favor_payout_last": 157, "total_domination": 7, "uneven_bet_add1": 3}, "4": {"favor_payout_richest": 143, "uneven_bet_bankCover": 6, "favor_payout_last": 15, "total_domination": 7, "uneven_bet_add1": 7}}}}