{"schema": 4, "pid": 14112, "written_at": "2025-09-10T03-24-02", "stats": {"play": {"Card(D, 11)": {"evals": 86, "sum_wins_evals": 618, "sum_losses_evals": 1194, "sum_total_candidates_evals": 2053, "certain_evals": 60, "plays": 11, "sum_wins_played": 227, "sum_losses_played": 75, "sum_total_candidates_played": 309, "certain_plays": 4}, "Card(A, 11)": {"evals": 82, "sum_wins_evals": 703, "sum_losses_evals": 827, "sum_total_candidates_evals": 1707, "certain_evals": 59, "plays": 19, "sum_wins_played": 325, "sum_losses_played": 95, "sum_total_candidates_played": 437, "certain_plays": 10}, "Card(B, 11)": {"evals": 61, "sum_wins_evals": 616, "sum_losses_evals": 577, "sum_total_candidates_evals": 1299, "certain_evals": 40, "plays": 13, "sum_wins_played": 253, "sum_losses_played": 58, "sum_total_candidates_played": 311, "certain_plays": 6}, "Card(A, 1)": {"evals": 99, "sum_wins_evals": 618, "sum_losses_evals": 1744, "sum_total_candidates_evals": 2549, "certain_evals": 52, "plays": 19, "sum_wins_played": 82, "sum_losses_played": 239, "sum_total_candidates_played": 345, "certain_plays": 12}, "Card(B, 7)": {"evals": 211, "sum_wins_evals": 1874, "sum_losses_evals": 2381, "sum_total_candidates_evals": 4717, "certain_evals": 111, "plays": 30, "sum_wins_played": 299, "sum_losses_played": 211, "sum_total_candidates_played": 548, "certain_plays": 15}, "Card(A, 3)": {"evals": 115, "sum_wins_evals": 931, "sum_losses_evals": 1869, "sum_total_candidates_evals": 3033, "certain_evals": 62, "plays": 20, "sum_wins_played": 164, "sum_losses_played": 219, "sum_total_candidates_played": 407, "certain_plays": 11}, "Card(B, 5)": {"evals": 205, "sum_wins_evals": 1792, "sum_losses_evals": 2246, "sum_total_candidates_evals": 4398, "certain_evals": 108, "plays": 33, "sum_wins_played": 430, "sum_losses_played": 275, "sum_total_candidates_played": 739, "certain_plays": 12}, "Card(A, 5)": {"evals": 191, "sum_wins_evals": 1968, "sum_losses_evals": 2371, "sum_total_candidates_evals": 4679, "certain_evals": 99, "plays": 31, "sum_wins_played": 489, "sum_losses_played": 250, "sum_total_candidates_played": 760, "certain_plays": 10}, "Card(B, 3)": {"evals": 87, "sum_wins_evals": 779, "sum_losses_evals": 1366, "sum_total_candidates_evals": 2262, "certain_evals": 35, "plays": 16, "sum_wins_played": 181, "sum_losses_played": 219, "sum_total_candidates_played": 418, "certain_plays": 5}, "Card(E, 1)": {"evals": 90, "sum_wins_evals": 573, "sum_losses_evals": 1193, "sum_total_candidates_evals": 1804, "certain_evals": 39, "plays": 19, "sum_wins_played": 107, "sum_losses_played": 207, "sum_total_candidates_played": 320, "certain_plays": 9}, "Card(D, 5)": {"evals": 198, "sum_wins_evals": 1478, "sum_losses_evals": 2334, "sum_total_candidates_evals": 4201, "certain_evals": 112, "plays": 29, "sum_wins_played": 357, "sum_losses_played": 219, "sum_total_candidates_played": 605, "certain_plays": 11}, "Card(A, 7)": {"evals": 211, "sum_wins_evals": 1894, "sum_losses_evals": 2236, "sum_total_candidates_evals": 4590, "certain_evals": 132, "plays": 29, "sum_wins_played": 451, "sum_losses_played": 153, "sum_total_candidates_played": 630, "certain_plays": 12}, "Card(A, 10)": {"evals": 96, "sum_wins_evals": 918, "sum_losses_evals": 977, "sum_total_candidates_evals": 2068, "certain_evals": 63, "plays": 14, "sum_wins_played": 324, "sum_losses_played": 47, "sum_total_candidates_played": 371, "certain_plays": 3}, "Card(B, 10)": {"evals": 80, "sum_wins_evals": 987, "sum_losses_evals": 699, "sum_total_candidates_evals": 1791, "certain_evals": 36, "plays": 17, "sum_wins_played": 291, "sum_losses_played": 128, "sum_total_candidates_played": 433, "certain_plays": 5}, "Card(E, 11)": {"evals": 67, "sum_wins_evals": 769, "sum_losses_evals": 668, "sum_total_candidates_evals": 1533, "certain_evals": 36, "plays": 16, "sum_wins_played": 215, "sum_losses_played": 112, "sum_total_candidates_played": 341, "certain_plays": 8}, "Card(D, 10)": {"evals": 89, "sum_wins_evals": 491, "sum_losses_evals": 1367, "sum_total_candidates_evals": 2142, "certain_evals": 65, "plays": 15, "sum_wins_played": 199, "sum_losses_played": 129, "sum_total_candidates_played": 345, "certain_plays": 7}, "Card(D, 1)": {"evals": 122, "sum_wins_evals": 666, "sum_losses_evals": 2053, "sum_total_candidates_evals": 2961, "certain_evals": 64, "plays": 19, "sum_wins_played": 100, "sum_losses_played": 274, "sum_total_candidates_played": 402, "certain_plays": 10}, "Card(E, 7)": {"evals": 188, "sum_wins_evals": 1830, "sum_losses_evals": 1840, "sum_total_candidates_evals": 3911, "certain_evals": 92, "plays": 31, "sum_wins_played": 393, "sum_losses_played": 192, "sum_total_candidates_played": 603, "certain_plays": 13}, "Card(E, 3)": {"evals": 98, "sum_wins_evals": 684, "sum_losses_evals": 896, "sum_total_candidates_evals": 1630, "certain_evals": 52, "plays": 14, "sum_wins_played": 111, "sum_losses_played": 106, "sum_total_candidates_played": 223, "certain_plays": 7}, "Card(C, 9)": {"evals": 89, "sum_wins_evals": 1088, "sum_losses_evals": 905, "sum_total_candidates_evals": 2085, "certain_evals": 42, "plays": 17, "sum_wins_played": 258, "sum_losses_played": 78, "sum_total_candidates_played": 336, "certain_plays": 7}, "Card(B, 9)": {"evals": 106, "sum_wins_evals": 981, "sum_losses_evals": 1136, "sum_total_candidates_evals": 2307, "certain_evals": 59, "plays": 18, "sum_wins_played": 294, "sum_losses_played": 133, "sum_total_candidates_played": 435, "certain_plays": 6}, "Card(D, 9)": {"evals": 77, "sum_wins_evals": 749, "sum_losses_evals": 974, "sum_total_candidates_evals": 1868, "certain_evals": 34, "plays": 15, "sum_wins_played": 223, "sum_losses_played": 108, "sum_total_candidates_played": 344, "certain_plays": 5}, "Card(E, 9)": {"evals": 103, "sum_wins_evals": 976, "sum_losses_evals": 954, "sum_total_candidates_evals": 2026, "certain_evals": 58, "plays": 13, "sum_wins_played": 154, "sum_losses_played": 66, "sum_total_candidates_played": 220, "certain_plays": 6}, "Card(C, 5)": {"evals": 212, "sum_wins_evals": 2150, "sum_losses_evals": 2083, "sum_total_candidates_evals": 4516, "certain_evals": 103, "plays": 33, "sum_wins_played": 435, "sum_losses_played": 268, "sum_total_candidates_played": 734, "certain_plays": 12}, "Card(D, 3)": {"evals": 117, "sum_wins_evals": 584, "sum_losses_evals": 1590, "sum_total_candidates_evals": 2380, "certain_evals": 70, "plays": 17, "sum_wins_played": 105, "sum_losses_played": 163, "sum_total_candidates_played": 280, "certain_plays": 10}, "Card(C, 7)": {"evals": 161, "sum_wins_evals": 1739, "sum_losses_evals": 1606, "sum_total_candidates_evals": 3544, "certain_evals": 78, "plays": 31, "sum_wins_played": 442, "sum_losses_played": 202, "sum_total_candidates_played": 666, "certain_plays": 12}, "Card(A, 9)": {"evals": 93, "sum_wins_evals": 749, "sum_losses_evals": 809, "sum_total_candidates_evals": 1717, "certain_evals": 65, "plays": 16, "sum_wins_played": 292, "sum_losses_played": 72, "sum_total_candidates_played": 372, "certain_plays": 6}, "Card(E, 5)": {"evals": 228, "sum_wins_evals": 1535, "sum_losses_evals": 2494, "sum_total_candidates_evals": 4343, "certain_evals": 132, "plays": 30, "sum_wins_played": 293, "sum_losses_played": 276, "sum_total_candidates_played": 596, "certain_plays": 14}, "Card(C, 1)": {"evals": 92, "sum_wins_evals": 685, "sum_losses_evals": 1363, "sum_total_candidates_evals": 2148, "certain_evals": 42, "plays": 19, "sum_wins_played": 160, "sum_losses_played": 283, "sum_total_candidates_played": 458, "certain_plays": 7}, "Card(E, 10)": {"evals": 93, "sum_wins_evals": 845, "sum_losses_evals": 1126, "sum_total_candidates_evals": 2158, "certain_evals": 50, "plays": 17, "sum_wins_played": 256, "sum_losses_played": 141, "sum_total_candidates_played": 409, "certain_plays": 6}, "Card(C, 11)": {"evals": 87, "sum_wins_evals": 1265, "sum_losses_evals": 680, "sum_total_candidates_evals": 2008, "certain_evals": 42, "plays": 17, "sum_wins_played": 381, "sum_losses_played": 75, "sum_total_candidates_played": 456, "certain_plays": 7}, "Card(C, 10)": {"evals": 84, "sum_wins_evals": 829, "sum_losses_evals": 503, "sum_total_candidates_evals": 1379, "certain_evals": 51, "plays": 17, "sum_wins_played": 246, "sum_losses_played": 81, "sum_total_candidates_played": 333, "certain_plays": 8}, "Card(C, 3)": {"evals": 100, "sum_wins_evals": 850, "sum_losses_evals": 1586, "sum_total_candidates_evals": 2508, "certain_evals": 37, "plays": 18, "sum_wins_played": 159, "sum_losses_played": 208, "sum_total_candidates_played": 373, "certain_plays": 7}, "Card(B, 1)": {"evals": 100, "sum_wins_evals": 628, "sum_losses_evals": 1792, "sum_total_candidates_evals": 2640, "certain_evals": 44, "plays": 17, "sum_wins_played": 115, "sum_losses_played": 269, "sum_total_candidates_played": 415, "certain_plays": 7}, "Card(D, 7)": {"evals": 202, "sum_wins_evals": 1226, "sum_losses_evals": 2413, "sum_total_candidates_evals": 4125, "certain_evals": 128, "plays": 30, "sum_wins_played": 251, "sum_losses_played": 188, "sum_total_candidates_played": 485, "certain_plays": 18}}, "bet": {"Card(A, 9)": {"evals": 12, "sum_wins_evals": 66, "sum_losses_evals": 16, "sum_total_candidates_evals": 82, "certain_evals": 6, "plays": 12, "sum_wins_played": 66, "sum_losses_played": 16, "sum_total_candidates_played": 82, "certain_plays": 6}, "Card(B, 5)": {"evals": 27, "sum_wins_evals": 91, "sum_losses_evals": 62, "sum_total_candidates_evals": 157, "certain_evals": 10, "plays": 27, "sum_wins_played": 91, "sum_losses_played": 62, "sum_total_candidates_played": 157, "certain_plays": 10}, "Card(E, 10)": {"evals": 15, "sum_wins_evals": 61, "sum_losses_evals": 28, "sum_total_candidates_evals": 96, "certain_evals": 6, "plays": 15, "sum_wins_played": 61, "sum_losses_played": 28, "sum_total_candidates_played": 96, "certain_plays": 6}, "Card(E, 3)": {"evals": 12, "sum_wins_evals": 25, "sum_losses_evals": 45, "sum_total_candidates_evals": 76, "certain_evals": 4, "plays": 12, "sum_wins_played": 25, "sum_losses_played": 45, "sum_total_candidates_played": 76, "certain_plays": 4}, "Card(B, 9)": {"evals": 14, "sum_wins_evals": 50, "sum_losses_evals": 40, "sum_total_candidates_evals": 98, "certain_evals": 7, "plays": 14, "sum_wins_played": 50, "sum_losses_played": 40, "sum_total_candidates_played": 98, "certain_plays": 7}, "Card(A, 5)": {"evals": 26, "sum_wins_evals": 77, "sum_losses_evals": 79, "sum_total_candidates_evals": 157, "certain_evals": 17, "plays": 26, "sum_wins_played": 77, "sum_losses_played": 79, "sum_total_candidates_played": 157, "certain_plays": 17}, "Card(A, 10)": {"evals": 10, "sum_wins_evals": 50, "sum_losses_evals": 7, "sum_total_candidates_evals": 57, "certain_evals": 5, "plays": 10, "sum_wins_played": 50, "sum_losses_played": 7, "sum_total_candidates_played": 57, "certain_plays": 5}, "Card(E, 7)": {"evals": 27, "sum_wins_evals": 94, "sum_losses_evals": 81, "sum_total_candidates_evals": 177, "certain_evals": 14, "plays": 27, "sum_wins_played": 94, "sum_losses_played": 81, "sum_total_candidates_played": 177, "certain_plays": 14}, "Card(A, 7)": {"evals": 26, "sum_wins_evals": 97, "sum_losses_evals": 42, "sum_total_candidates_evals": 155, "certain_evals": 14, "plays": 26, "sum_wins_played": 97, "sum_losses_played": 42, "sum_total_candidates_played": 155, "certain_plays": 14}, "Card(A, 11)": {"evals": 17, "sum_wins_evals": 66, "sum_losses_evals": 17, "sum_total_candidates_evals": 104, "certain_evals": 13, "plays": 17, "sum_wins_played": 66, "sum_losses_played": 17, "sum_total_candidates_played": 104, "certain_plays": 13}, "Card(B, 11)": {"evals": 9, "sum_wins_evals": 51, "sum_losses_evals": 14, "sum_total_candidates_evals": 65, "certain_evals": 4, "plays": 9, "sum_wins_played": 51, "sum_losses_played": 14, "sum_total_candidates_played": 65, "certain_plays": 4}, "Card(B, 7)": {"evals": 19, "sum_wins_evals": 71, "sum_losses_evals": 41, "sum_total_candidates_evals": 125, "certain_evals": 10, "plays": 19, "sum_wins_played": 71, "sum_losses_played": 41, "sum_total_candidates_played": 125, "certain_plays": 10}, "Card(C, 1)": {"evals": 17, "sum_wins_evals": 10, "sum_losses_evals": 95, "sum_total_candidates_evals": 113, "certain_evals": 12, "plays": 17, "sum_wins_played": 10, "sum_losses_played": 95, "sum_total_candidates_played": 113, "certain_plays": 12}, "Card(C, 7)": {"evals": 28, "sum_wins_evals": 93, "sum_losses_evals": 59, "sum_total_candidates_evals": 159, "certain_evals": 15, "plays": 28, "sum_wins_played": 93, "sum_losses_played": 59, "sum_total_candidates_played": 159, "certain_plays": 15}, "Card(C, 10)": {"evals": 14, "sum_wins_evals": 62, "sum_losses_evals": 23, "sum_total_candidates_evals": 85, "certain_evals": 5, "plays": 14, "sum_wins_played": 62, "sum_losses_played": 23, "sum_total_candidates_played": 85, "certain_plays": 5}, "Card(E, 9)": {"evals": 10, "sum_wins_evals": 45, "sum_losses_evals": 17, "sum_total_candidates_evals": 62, "certain_evals": 5, "plays": 10, "sum_wins_played": 45, "sum_losses_played": 17, "sum_total_candidates_played": 62, "certain_plays": 5}, "Card(D, 3)": {"evals": 15, "sum_wins_evals": 17, "sum_losses_evals": 72, "sum_total_candidates_evals": 90, "certain_evals": 10, "plays": 15, "sum_wins_played": 17, "sum_losses_played": 72, "sum_total_candidates_played": 90, "certain_plays": 10}, "Card(C, 5)": {"evals": 27, "sum_wins_evals": 96, "sum_losses_evals": 56, "sum_total_candidates_evals": 161, "certain_evals": 13, "plays": 27, "sum_wins_played": 96, "sum_losses_played": 56, "sum_total_candidates_played": 161, "certain_plays": 13}, "Card(E, 11)": {"evals": 13, "sum_wins_evals": 63, "sum_losses_evals": 13, "sum_total_candidates_evals": 83, "certain_evals": 7, "plays": 13, "sum_wins_played": 63, "sum_losses_played": 13, "sum_total_candidates_played": 83, "certain_plays": 7}, "Card(B, 10)": {"evals": 16, "sum_wins_evals": 52, "sum_losses_evals": 46, "sum_total_candidates_evals": 105, "certain_evals": 11, "plays": 16, "sum_wins_played": 52, "sum_losses_played": 46, "sum_total_candidates_played": 105, "certain_plays": 11}, "Card(B, 3)": {"evals": 11, "sum_wins_evals": 25, "sum_losses_evals": 40, "sum_total_candidates_evals": 66, "certain_evals": 6, "plays": 11, "sum_wins_played": 25, "sum_losses_played": 40, "sum_total_candidates_played": 66, "certain_plays": 6}, "Card(D, 5)": {"evals": 22, "sum_wins_evals": 66, "sum_losses_evals": 70, "sum_total_candidates_evals": 147, "certain_evals": 9, "plays": 22, "sum_wins_played": 66, "sum_losses_played": 70, "sum_total_candidates_played": 147, "certain_plays": 9}, "Card(C, 9)": {"evals": 16, "sum_wins_evals": 80, "sum_losses_evals": 26, "sum_total_candidates_evals": 106, "certain_evals": 7, "plays": 16, "sum_wins_played": 80, "sum_losses_played": 26, "sum_total_candidates_played": 106, "certain_plays": 7}, "Card(D, 1)": {"evals": 16, "sum_wins_evals": 16, "sum_losses_evals": 76, "sum_total_candidates_evals": 95, "certain_evals": 10, "plays": 16, "sum_wins_played": 16, "sum_losses_played": 76, "sum_total_candidates_played": 95, "certain_plays": 10}, "Card(E, 1)": {"evals": 14, "sum_wins_evals": 7, "sum_losses_evals": 75, "sum_total_candidates_evals": 83, "certain_evals": 10, "plays": 14, "sum_wins_played": 7, "sum_losses_played": 75, "sum_total_candidates_played": 83, "certain_plays": 10}, "Card(A, 3)": {"evals": 16, "sum_wins_evals": 24, "sum_losses_evals": 61, "sum_total_candidates_evals": 94, "certain_evals": 10, "plays": 16, "sum_wins_played": 24, "sum_losses_played": 61, "sum_total_candidates_played": 94, "certain_plays": 10}, "Card(A, 1)": {"evals": 15, "sum_wins_evals": 27, "sum_losses_evals": 81, "sum_total_candidates_evals": 108, "certain_evals": 9, "plays": 15, "sum_wins_played": 27, "sum_losses_played": 81, "sum_total_candidates_played": 108, "certain_plays": 9}, "Card(C, 11)": {"evals": 15, "sum_wins_evals": 74, "sum_losses_evals": 24, "sum_total_candidates_evals": 98, "certain_evals": 10, "plays": 15, "sum_wins_played": 74, "sum_losses_played": 24, "sum_total_candidates_played": 98, "certain_plays": 10}, "Card(E, 5)": {"evals": 28, "sum_wins_evals": 86, "sum_losses_evals": 78, "sum_total_candidates_evals": 177, "certain_evals": 12, "plays": 28, "sum_wins_played": 86, "sum_losses_played": 78, "sum_total_candidates_played": 177, "certain_plays": 12}, "Card(C, 3)": {"evals": 15, "sum_wins_evals": 33, "sum_losses_evals": 53, "sum_total_candidates_evals": 86, "certain_evals": 8, "plays": 15, "sum_wins_played": 33, "sum_losses_played": 53, "sum_total_candidates_played": 86, "certain_plays": 8}, "Card(D, 7)": {"evals": 24, "sum_wins_evals": 76, "sum_losses_evals": 57, "sum_total_candidates_evals": 146, "certain_evals": 14, "plays": 24, "sum_wins_played": 76, "sum_losses_played": 57, "sum_total_candidates_played": 146, "certain_plays": 14}, "Card(B, 1)": {"evals": 14, "sum_wins_evals": 12, "sum_losses_evals": 72, "sum_total_candidates_evals": 86, "certain_evals": 8, "plays": 14, "sum_wins_played": 12, "sum_losses_played": 72, "sum_total_candidates_played": 86, "certain_plays": 8}, "Card(D, 10)": {"evals": 13, "sum_wins_evals": 51, "sum_losses_evals": 25, "sum_total_candidates_evals": 77, "certain_evals": 6, "plays": 13, "sum_wins_played": 51, "sum_losses_played": 25, "sum_total_candidates_played": 77, "certain_plays": 6}, "Card(D, 11)": {"evals": 11, "sum_wins_evals": 56, "sum_losses_evals": 28, "sum_total_candidates_evals": 84, "certain_evals": 7, "plays": 11, "sum_wins_played": 56, "sum_losses_played": 28, "sum_total_candidates_played": 84, "certain_plays": 7}, "Card(D, 9)": {"evals": 7, "sum_wins_evals": 22, "sum_losses_evals": 21, "sum_total_candidates_evals": 49, "certain_evals": 3, "plays": 7, "sum_wins_played": 22, "sum_losses_played": 21, "sum_total_candidates_played": 49, "certain_plays": 3}}, "outcome": {"Card(A, 11)": {"wins": 12, "losses": 7, "wins_by_concede": 7, "losses_by_concede": 5}, "Card(A, 10)": {"wins": 7, "losses": 7, "wins_by_concede": 4, "losses_by_concede": 6}, "Card(B, 11)": {"wins": 8, "losses": 5, "wins_by_concede": 1, "losses_by_concede": 5}, "Card(E, 3)": {"wins": 6, "losses": 8, "wins_by_concede": 2, "losses_by_concede": 5}, "Card(A, 9)": {"wins": 9, "losses": 7, "wins_by_concede": 5, "losses_by_concede": 3}, "Card(B, 7)": {"wins": 19, "losses": 11, "wins_by_concede": 8, "losses_by_concede": 6}, "Card(B, 9)": {"wins": 10, "losses": 8, "wins_by_concede": 6, "losses_by_concede": 4}, "Card(E, 7)": {"wins": 18, "losses": 13, "wins_by_concede": 10, "losses_by_concede": 7}, "Card(A, 7)": {"wins": 19, "losses": 10, "wins_by_concede": 13, "losses_by_concede": 6}, "Card(B, 5)": {"wins": 14, "losses": 19, "wins_by_concede": 6, "losses_by_concede": 11}, "Card(E, 10)": {"wins": 11, "losses": 6, "wins_by_concede": 7, "losses_by_concede": 3}, "Card(A, 5)": {"wins": 12, "losses": 19, "wins_by_concede": 5, "losses_by_concede": 11}, "Card(E, 11)": {"wins": 11, "losses": 5, "wins_by_concede": 8, "losses_by_concede": 4}, "Card(E, 9)": {"wins": 9, "losses": 4, "wins_by_concede": 3, "losses_by_concede": 2}, "Card(C, 1)": {"wins": 5, "losses": 14, "wins_by_concede": 4, "losses_by_concede": 10}, "Card(B, 3)": {"wins": 1, "losses": 15, "wins_by_concede": 1, "losses_by_concede": 8}, "Card(B, 10)": {"wins": 10, "losses": 7, "wins_by_concede": 6, "losses_by_concede": 7}, "Card(D, 3)": {"wins": 4, "losses": 13, "wins_by_concede": 1, "losses_by_concede": 6}, "Card(C, 7)": {"wins": 14, "losses": 17, "wins_by_concede": 11, "losses_by_concede": 12}, "Card(C, 10)": {"wins": 10, "losses": 7, "wins_by_concede": 6, "losses_by_concede": 4}, "Card(C, 5)": {"wins": 18, "losses": 15, "wins_by_concede": 13, "losses_by_concede": 10}, "Card(E, 1)": {"wins": 5, "losses": 14, "wins_by_concede": 4, "losses_by_concede": 6}, "Card(A, 3)": {"wins": 6, "losses": 14, "wins_by_concede": 3, "losses_by_concede": 5}, "Card(D, 5)": {"wins": 13, "losses": 16, "wins_by_concede": 8, "losses_by_concede": 8}, "Card(A, 1)": {"wins": 4, "losses": 15, "wins_by_concede": 4, "losses_by_concede": 6}, "Card(C, 9)": {"wins": 15, "losses": 2, "wins_by_concede": 8, "losses_by_concede": 1}, "Card(D, 1)": {"wins": 5, "losses": 14, "wins_by_concede": 3, "losses_by_concede": 6}, "Card(E, 5)": {"wins": 21, "losses": 9, "wins_by_concede": 11, "losses_by_concede": 5}, "Card(C, 11)": {"wins": 12, "losses": 5, "wins_by_concede": 8, "losses_by_concede": 4}, "Card(C, 3)": {"wins": 8, "losses": 10, "wins_by_concede": 5, "losses_by_concede": 4}, "Card(D, 7)": {"wins": 17, "losses": 13, "wins_by_concede": 8, "losses_by_concede": 9}, "Card(D, 9)": {"wins": 8, "losses": 7, "wins_by_concede": 2, "losses_by_concede": 3}, "Card(B, 1)": {"wins": 4, "losses": 13, "wins_by_concede": 4, "losses_by_concede": 5}, "Card(D, 10)": {"wins": 9, "losses": 6, "wins_by_concede": 5, "losses_by_concede": 3}, "Card(D, 11)": {"wins": 6, "losses": 5, "wins_by_concede": 3, "losses_by_concede": 3}}, "coins": {"1": {"uneven_bet_bankCover": 7, "uneven_bet_add1": 13, "total_domination": 5, "favor_payout_richest": 23, "favor_payout_last": 111}, "2": {"uneven_bet_bankCover": 7, "uneven_bet_add1": 17, "total_domination": 17, "favor_payout_richest": 74, "favor_payout_last": 108}, "3": {"uneven_bet_bankCover": 2, "uneven_bet_add1": 12, "total_domination": 11, "favor_payout_richest": 59, "favor_payout_last": 124}, "4": {"uneven_bet_bankCover": 2, "uneven_bet_add1": 11, "total_domination": 17, "favor_payout_richest": 149, "favor_payout_last": 95}}}}